Workbook

Sheet RSVPs - July 23
A1: name | B1: first_name | C1: last_name | D1: email | E1: Job Title | F1: Company | G1: Type of Company | H1: Email | I1: Telegram | J1: What's your LinkedIn ? | K1: Kindly provide the name of the person who invited you to this event
A2: Asi Burak | D2: aburak@tiltingpoint.com | E2: CBO | F2: Tilting Point | G2: Games | H2: aburak@tiltingpoint.com | J2: https://www.linkedin.com/in/asiburak/ | K2: Marina Espin
A3: Alex Crawford | B3: Alex | C3: Crawford | D3: alex.crawford@immutable.com | E3: Enterprise BDM | F3: Immutable | G3: Blockchain | H3: alex.crawford@immutable.com | I3: @alex_crawf | J3: https://www.linkedin.com/in/alexcrawfordau/ | K3: Sergio / Kamil
A4: Anna Kuzmenko | B4: Anna | C4: Kuzmenko | D4: anna.kuzmenko@immutable.com | E4: BD Manager APAC | F4: Immutable | G4: Games | H4: anna.kuzmenko@immutable.com | I4: immutanna | J4: https://linkedin.com/in/anna-kuzmenko | K4: Immutable team
A5: Antonio Guaranys | D5: antonio.guaranys@hermitcrabstudio.com | E5: Business Developer | F5: Hermit Crab | G5: Game Studio | H5: antonio.guaranys@hermitcrabstudio.com | J5: www.linkedin.com/in/antonioguaranys | K5: Trapper
A6: Ataberk Ates | B6: Ataberk | C6: Ates | D6: ataberk@ataberkates.com | E6: Lead Designer | F6: Climax Studios | G6: Game Studio | H6: ataberk@ataberkates.com | J6: https://www.linkedin.com/in/ataberkates/ | K6: -
A7: Polygon Labs | B7: Blake | C7: Payne | D7: bpayne@polygon.technology | E7: Manager | F7: Polygon | G7: Infrastructure | H7: bpayne@polygon.technology | J7: https://linkedin.com/in/blakefpayne | K7: Max
A8: Bret Curan | B8: Bret | C8: Curan | D8: bret@lightningforge.games | E8: Chief Product Officer / Co-founder | F8: Lightning Forge Games | G8: AI, Game Studio | H8: bret@lightningforge.games | I8: @BusinessCatAU | J8: https://linkedin.com/in/bret-curan-092b82256 | K8: Max Kaufman
A9: Caio Filizola | B9: Caio | C9: Filizola | D9: caiofilizola@cyanheartstudio.com | E9: CEO | F9: Cyan Heart Studio | G9: Games | H9: caiofilizola@cyanheartstudio.com | J9: https://www.linkedin.com/in/caio-filizola/ | K9: N/A
A10: chris castagnetto | B10: Chris | C10: Castagnetto | D10: ccas121@gmail.com | E10: Business Development | F10: TikTok | G10: Others | H10: ccas121@gmail.com | J10: https://www.linkedin.com/in/ccastagnetto/ | K10: web list
A11: Cecilia | D11: cecilia.fadul@kwalee.com | E11: Head of AdMonetisation | F11: Kwalee | G11: Games | H11: cecilia.fadul@kwalee.com | J11: https://www.linkedin.com/in/ceciliafadul/ | K11: slack
A12: Romain Schneider | B12: Romain | C12: Schneider | D12: ceo@spectarium.games | E12: CEO and Founder | F12: Spectarium Games | G12: Games | H12: Ceo@spectarium.games | J12: linkedin.com/in/rdgs15 | K12: Sam, WolvesDAO
A13: Chris Keeling | D13: chris@marsgames.com | E13: CEO | F13: Mars Games | G13: Games | H13: chris@marsgames.com | J13: https://www.linkedin.com/in/chriskeeling/ | K13: Mattie Fairchild
A14: Ciaran Daly | D14: ciaran.daly@twistedworks.com | E14: Director | F14: Twisted Works | G14: Games, Media | H14: ciaran.daly@twistedworks.com | J14: https://www.linkedin.com/in/ciarandaly/ | K14: N/A
A15: David Boileau | B15: David | C15: Boileau | D15: dave.boileau@gamebreaking.com | E15: Senior Engineering Manager | F15: Gamebreaking Studios | G15: Game Studio | H15: dave.boileau@gamebreaking.com | J15: https://www.linkedin.com/in/davidboileau/ | K15: Grace Zhou
A16: Diego Beltrame | B16: Diego | C16: Beltrame | D16: diego.beltrame@unity3d.com | E16: Sr Client Partner | F16: Unity Multiplay | G16: Infrastructure | H16: diego.beltrame@unity3d.com | J16: https://www.linkedin.com/in/beltramediego/ | K16: working with Web3 customers
A17: Elena Provine | B17: Elena | C17: Provine | D17: elena@equitywestadvisors.com | E17: Venture Partner | F17: Griffin Gaming | G17: VC | H17: elena@equitywestadvisors.com | I17: lena_provine | J17: https://www.linkedin.com/in/elenaprovine/ | K17: Greg Labuz
A18: flavia | B18: Flavia | D18: flavia.luz@webcore.com.br | E18: Operations | F18: Webcore Games | G18: Games | H18: flavia.luz@webcore.com.br | I18: 5511992077151 | J18: https://www.linkedin.com/in/flavialuz/ | K18: Grace Zhou
A19: Fred @ Funfair Ventures | B19: Fred | D19: frederico.kessler@funfair.io | E19: Partner | F19: Funfair ventures | G19: VC | H19: Frederico.kessler@funfair.io | I19: Fr3dsk | J19: https://linkedin.com/in/fr3dk | K19: Found it on luma
A20: GaspodeWD // Felix | B20: Felix | C20: Bracher | D20: gaspodewd@whatsyourgam3.com | E20: CSO // Head Of Marketing | F20: FDF // G3 | G20: Media | H20: gaspodewd@whatsyourgam3.com | J20: https://www.linkedin.com/in/felix-bracher/ | K20: Big Dog Max
A21: Georg Broxtermann | B21: Georg | C21: Broxtermann | D21: georg@gameinfluencer.com | E21: CEO | F21: GameInfluencer.com | G21: Media | H21: georg@gameinfluencer.com | J21: https://linkedin.com/in/broxtermann | K21: Sergio Varona Bustillo
A22: Grace Zhou | B22: Grace | C22: Zhou | D22: gracemin.zhou@gmail.com | E22: Director of Corp Dev | F22: Scopely | G22: Games | H22: grace.zhou@scopely.com | J22: https://linkedin.com/in/graceminzhou | K22: Polygon
A23: Gunjan Sharman | B23: Gunjan | C23: Sharman | D23: gunjan@beamable.com | E23: VP of Product | F23: Beamable | G23: Infrastructure | H23: gunjan@beamable.com | I23: i_gsharman | J23: https://linkedin.com/in/gsharman | K23: Max Kauffman
A24: Haye Anderson | B24: Haye | C24: Anderson | D24: haye.anderson@ubisoft.com | E24: Brand Director | F24: Ubisoft | G24: Game Studio | H24: Haye.anderson@ubisoft.com | J24: https://www.linkedin.com/in/andersonhayley/ | K24: Alex Brodsky
A25: Marcus Krautwurst | B25: Marcus | C25: Krautwurst | D25: hello@monster-puppet.com | E25: CEO | F25: Monster Puppet Corporation | G25: Games | H25: hello@monster-puppet.com | J25: https://www.linkedin.com/in/mkrautwurst?utm_source=share&utm_campaign=share_via&utm_content=profile&utm_medium=ios_app | K25: Hind
A26: Jan Roessner | B26: Jan | C26: Roessner | D26: jan@oneearthrising.com | E26: CEO | F26: One Earth Rising | G26: Infrastructure | H26: jan@oneearthrising.com | I26: @janroessner | J26: https://linkedin.com/in/janroessner | K26: Max Kaufman
A27: Joachim Rittfeldt Hofvenschiöld | B27: Joachim | C27: Rittfeldt Hofvenschiöld | D27: joachim@spectarium.games | E27: BD / Investor | F27: Spectarium Games / uBIT.vc | G27: Games, VC | H27: Joachim@ubit.vc | I27: Hofvenschiold | J27: Linkedin.com/in/hofven | K27: Sam, WolvesDAO
A28: John Bergman | D28: john@guildsoftware.com | E28: CEO | F28: Guild Software | G28: Game Studio, Game Publisher | H28: john@guildsoftware.com | I28: @JohnBergman | J28: linkedin.com/in/incarnate | K28: Grace Zhou's secret telegram thing. We have a live MMORPG with substantial users, considering possible blockchain partners.
A29: Justin Edwards | B29: Justin | C29: Edwards | D29: justin@twintec.io | E29: CPO | F29: WARP | G29: Game Publisher, Infrastructure, Blockchain | H29: Justin@twintec.io | I29: Juzzy007 | J29: https://www.linkedin.com/in/justin-edwards-876a193/ | K29: Matthew Buxton
A30: Kate Edwards | D30: kate@geogrify.com | E30: CEO / CXO & Cofounder | F30: Geogrify / SetJetters | G30: Others | H30: kate@geogrify.com | J30: https://www.linkedin.com/in/geogrify/ | K30: Hind Toufga
A31: Keith Flynn | B31: Keith | C31: Flynn | D31: keith.flynn@finoa.io | E31: Sr. Sales / Partnerships Manager | F31: Finoa | G31: Exchange, AI, Infrastructure | H31: keith.flynn@finoa.io | I31: @F_Keith | J31: https://www.linkedin.com/in/keith-flynn-/ | K31: Max via Jeremy Parris & Sonny Tsiopani
A32: Konrad Adamczewski | D32: konrad.adamczewski@11bitstudios.com | E32: Senior PR Manager | F32: 11 bit studios | G32: Game Publisher, Game Studio | H32: konrad.adamczewski@11bitstudios.com | J32: www.linkedin.com/in/konrad-adamczewski-292a26141 | K32: I just got a link from the list of events, honestly, so no direct person, unfortunately.
A33: Kristian | B33: Kristian | C33: Kolvek | D33: kristian@1minus1.com | E33: BD Manager at 1minus1 & BD Games Voice on Linkedin | F33: 1minus1 | G33: Others | H33: kristian@1minus1.com | J33: https://www.linkedin.com/in/kristiankolvek/ | K33: none
A34: Kevin Rubio | B34: Kevin | C34: Rubio | D34: krubio@tiltingpoint.com | E34: Director, Business Development | F34: Tilting Point | G34: Games | H34: krubio@tiltingpoint.com | J34: https://www.linkedin.com/in/kevin-rubio-ramirez/ | K34: Marina
A35: Krystian Jaroszynski | B35: Krystian | C35: Jaroszynski | D35: krystian@heroic.gg | E35: Chief commercial officer | F35: Heroic AS | G35: Others, Games | H35: krystian@heroic.gg | J35: www.linkedin.com/in/krystian-jaroszynski-80949437 | K35: Grace Zhou
A36: Kamil Zielinski | B36: Kamil | C36: Zielinski | D36: kzielinski@polygon.technology | E36: BD, Gaming | F36: Polygon Labs | G36: Blockchain, Games, Defi, Infrastructure | H36: kzielinski@polygon.technology | J36: www.linkedin.com/in/kzielinski94/ | K36: Sergio Varona, Max Kaufman, Blake Fuller
A37: Lisa-Maria Wittmann | B37: Lisa-Maria | C37: Wittmann | D37: lisa-maria.wittmann@ubisoft.com | E37: International Product Manager | F37: Ubisoft Mainz | G37: Game Studio | H37: lisa-maria.wittmann@ubisoft.com | J37: https://www.linkedin.com/in/lisamariawittmann/ | K37: Haye Anderson (Brand Director for Anno at Ubisoft Mainz)
A38: Marina | D38: marina@tiltingpoint.com | E38: VP of BD | F38: Tilting Point | G38: Games | H38: marina@tiltingpoint.com | J38: mespinfarran | K38: Sergio
A39: Martin Cao | B39: Martin | C39: Cao | D39: marto@martocao.com | E39: Partner | F39: Martocao | G39: Others | H39: marto@martocao.com | J39: https://www.linkedin.com/in/martincao/ | K39: .
A40: Marty Burgess | B40: Marty | C40: Burgess | D40: marty@lightningforge.games | E40: CEO | F40: Lightning Forge Games | G40: Game Studio | H40: marty@lightningforge.games | I40: @alcatrazzalz | J40: https://linkedin.com/in/marty-burgess | K40: Jas
A41: Matheus Vivian | B41: Matheus | C41: Vivian | D41: matheus@hermitcrabstudio.com | E41: CEO | F41: Hermit Crab Studio | G41: Game Studio | H41: matheus@hermitcrabstudio.com | J41: https://www.linkedin.com/in/matheus-vivian-3345a3114/ | K41: Trapper
A42: Matt Buxton | B42: Matt | C42: Buxton | D42: matt@mysticgames.dev | E42: CEO | F42: WARP CHAIN | G42: Blockchain, Infrastructure, Game Publisher, Wallet, AI | H42: matt@warpgaming.io | I42: @MattBuxton | J42: https://linkedin.com/in/matthewbuxton | K42: Max Kaufman
A43: Miguel | B43: Miguel | C43: Oliveira | D43: miguel@druids.ai | E43: CEO / Co-Founder | F43: Druids AI | G43: AI, Infrastructure, Others | H43: miguel@druids.ai | J43: https://linkedin.com/in/migueloliveira | K43: Harry
A44: Mike Fischer | D44: mike.fischer@krafton.com | E44: Executive Advisor | F44: Krafton | G44: Game Publisher | H44: mike.fischer@krafton.com | I44: @gamegoglobal | J44: https://www.linkedin.com/in/perrymichaelfischer/ | K44: Jay Zhao
A45: Thomas Müller | B45: Thomas | C45: Müller | D45: mueller@fs-studios.com | E45: CEO | F45: Fire Sword Studios | G45: Games | H45: mueller@fs-studios.com | J45: https://www.linkedin.com/in/speedybrain/ | K45: I am interested in polygon labs work
A46: Natasha Collin | D46: ncollin@ninedotsstudio.com | E46: COO and Executive Producer | F46: Nine Dots Studio inc | G46: Game Studio, Game Publisher | H46: ncollin@ninedotsstudio.com | J46: https://www.linkedin.com/in/natasha-collin-%F0%9F%94%9C-gamescom-673248169/ | K46: N/A
A47: Paul Thind | B47: Paul | C47: Thind | D47: paul@aethir.com | E47: Chief Revenue Officer | F47: Aethir | G47: Infrastructure | H47: Paul@aethir.com | I47: @paulthind | J47: www.linkedin.com/in/paulthind | K47: Grace and Many polygon team members
A48: Pontus Denlew | D48: pdenlew@havelii.com | E48: Investor | F48: Haveli Investments | G48: Games, VC | H48: pdenlew@havelii.com | J48: linkedin.com/in/pdenlew | K48: NA
A49: Philipp Karstaedt | B49: Philipp | C49: Karstaedt | D49: philipp@legendaryplay.gg | E49: CEO | F49: Legendary Play GmbH | G49: Games | H49: philipp@legendaryplay.gg | I49: phikappa | J49: phikappa | K49: Grace Zhou
A50: Puli Liyanagama | B50: Puli | C50: Liyanagama | D50: puli@metica.com | E50: CTO | F50: Metica | G50: AI | H50: Puli@metica.com | J50: www.linkedin.com/in/pulitha | K50: Mark
A51: richard mclean | B51: Richard | C51: Mclean | D51: richard.mclean@sensortower.com | E51: Account Director | F51: Sensor Tower | G51: Others | H51: richard.mclean@sensortower.com | J51: https://www.linkedin.com/in/richard-m-483192b7/ | K51: -
A52: Sony Joseph | B52: Sony | C52: Joseph | D52: sjoseph@gotartifact.com | E52: CEO / Founder | F52: Artifact Lab | G52: Games, Infrastructure, Blockchain, AI | H52: sjoseph@gotartifact.com | I52: sjsph | J52: https://www.linkedin.com/in/sonyj/ | K52: Sergio Varona
A53: Sonny Tsiopani | B53: Sonny | C53: Tsiopani | D53: sonny.tsiopani@pixiongames.com | E53: BD and Ecosystem Lead | F53: Pixion Games (Fableborne) | G53: Game Studio, Game Publisher, Blockchain | H53: sonny.tsiopani@pixiongames.com | I53: @positivesongame | J53: https://www.linkedin.com/in/sonny-tsiopani-87b372235/ | K53: Max
A54: Taylor Hellam | B54: Taylor | C54: Hellam | D54: taylor.hellam@gamebreaking.com | E54: CEO | F54: Gamebreaking Studios | G54: Game Studio | H54: taylor.hellam@gamebreaking.com | J54: https://www.linkedin.com/in/taylorhellam/ | K54: Grace Zhou
A55: Vitor Leães | D55: vitor@hermitcrabstudio.com | E55: Head of Product | F55: Hermit Crab Studio | G55: Game Studio | H55: vitor@hermitcrabstudio.com | J55: https://www.linkedin.com/in/vitor-severo-le%C3%A3es-13a50721/ | K55: Trapper
A56: Vladislav Tsopljak | B56: Vladislav | C56: Tsopljak | D56: vlad@neondoctrine.com | E56: Founder and CCO | F56: Neon Doctrine | G56: Games | H56: vlad@neondoctrine.com | I56: Stutsies | J56: https://www.linkedin.com/in/vladislav-tsypljak/ | K56: N/A
A57: wahid | B57: Wahid | C57: Abdollahiha | D57: wahid.abdollahiha@gmail.com | E57: Creative Director | F57: Zopyer | G57: Game Studio, Blockchain | H57: vahid.abdollahi@zopyer.com | I57: @wahidab | J57: https://linkedin.com/in/vahidabdollahiha | K57: max kaufman
A58: Warren Woodward | B58: Warren | C58: Woodward | D58: warrenwoodward@upptic.com | E58: Chief Growth Officer | F58: Upptic | G58: Games, Infrastructure | H58: warrenwoodward@uppticl.com | I58: bleedkale | J58: https://linkedin.com/in/warrendwoodward | K58: Wolves DAO Member
A59: Winston Petty | D59: winston@webcore.com.br | E59: Studio head | F59: Webcore games | G59: Games | H59: winston@webcore.com.br | I59: 5511982456177 | J59: https://www.linkedin.com/in/winstonpetty/ | K59: Grace Zhou
A60: Wook Kim | B60: Wook | C60: Kim | D60: wook.kim@wemade.com | E60: VP of Business & Operations | F60: Wemade/WEMIX | G60: Game Studio, Blockchain, Game Publisher | H60: wook.kim@wemade.com | I60: @k4k4shi121 | J60: https://www.linkedin.com/in/wook-kim-16b3332a/ | K60: Grace
A61: Liu | C61: Liu | D61: 451601810@qq.com | E61: manager | F61: SYS Tech | G61: AI | H61: 451601810@qq.com | J61: None | K61: Jack
A62: Xander Agosta | B62: Xander | C62: Agosta | D62: aagosta@upptic.com | E62: Director of Marketing and Partnerships | F62: Upptic | G62: Games | H62: aagosta@upptic.com | J62: https://linkedin.com/in/alexanderagosta | K62: Eric
A63: Adam | D63: adam@werocreative.com | E63: Founder | F63: Game Space Agency | G63: Games, AI | H63: adam@werocreative.com | J63: https://www.linkedin.com/in/adam-clare-7a41142/ | K63: N/A
A64: Alessandro Giovanetto | D64: ale@alessandro-giovanetto.com | E64: Composer | F64: Funny Ears Productions | G64: Games, Others | H64: ale@alessandro-giovanetto.com | J64: https://www.linkedin.com/in/alessandro-giovanetto-2665aa179/ | K64: Grace Zhou
A65: Alexander Hamparsomian | D65: alexander.hamparsomian@gmail.com | E65: COO | F65: Glimeria Studios AB | G65: Games | H65: alexander.hamparsomian@gmail.com | J65: https://www.linkedin.com/in/alexander-hamparsomian | K65: Grace Zhou
A66: Aleksandr Riabov | B66: Aleksandr | C66: Riabov | D66: alexr@imts.dev | E66: Business Development Director | F66: Immortals Studios | G66: Infrastructure, AI, Others | H66: alexr@imts.dev | J66: https://www.linkedin.com/in/alex-riabov1/ | K66: None
A67: Alfonso Ortiz Palma Junco | B67: Alfonso | C67: Ortiz Palma Junco | D67: alfonso.ortiz@tarutech.ai | E67: CCO | F67: Taru Tech | G67: AI | H67: alfonso.ortiz@tarutech.ai | J67: https://www.linkedin.com/in/ortizpalma/ | K67: Gamescom Events list
A68: Alisa Artemova | B68: Alisa | C68: Artemova | D68: alisa.artemova.v@gmail.com | E68: User Experience Researcher | F68: EPIC | G68: Games | H68: alisa.artemova.v@gmail.com | J68: https://www.linkedin.com/in/alisa-artemova/ | K68: Kami
A69: Andrew Pringle | B69: Andrew | C69: Pringle | D69: andy@yom.net | E69: CCO | F69: YOM | G69: Infrastructure, Games | H69: andy@yom.net | I69: https://t.me/laughing_buddha2 | J69: https://www.linkedin.com/in/pringleandrew/ | K69: Grace Zhou
A70: Antoine Jullemier | D70: antoine.jullemier@gadsme.com | E70: Head of Supply | F70: GADSME | G70: Games | H70: antoine.jullemier@gadsme.com | J70: https://www.linkedin.com/in/antoine-jlm/ | K70: /
A71: April Stallings | B71: April | C71: Stallings | D71: astallings@worldwish.org | E71: Charitable Gaming Manager | F71: Make-A-Wish International | G71: Others | H71: astallings@worldwish.org | J71: https://linkedin.com/in/aprilstallings | K71: Hindi
A72: Astrid Gooding | B72: Astrid | C72: Gooding | D72: astrid@elsewherenfp.com | E72: COO | F72: elsewhereNFP | G72: Others | H72: Astrid@elsewherenfp.com | J72: https://www.linkedin.com/in/astrid-gooding | K72: Michael
A73: Berkay Dursun | B73: Berkay | C73: Dursun | D73: berkayd@ioi.dk | E73: AI Programmer | F73: IO Interactive | G73: Game Studio | H73: berkayd@ioi.dk | J73: https://www.linkedin.com/in/berkaydursun/ | K73: -
A74: Cartic P | B74: Cartic | C74: P | D74: cartic@juegostudio.com | E74: AVP Games | F74: Juego Studio | G74: Games | H74: Cartic@juegostudio.com | I74: iCartic | J74: https://www.linkedin.com/in/icartic | K74: NA
A75: chris armbruster | B75: Chris | C75: Armbruster | D75: chris.armbruster@rocketscience.gg | E75: Client Partner | F75: Rocket Science Group | G75: Game Studio | H75: chris.armbruster@rocketscience.gg | J75: https://www.linkedin.com/in/chris-armbruster-🔜-gamescom-cologne-01100316/ | K75: Grace Zhou
A76: Chris O'Kelly | D76: chrisokelly@gmail.com | E76: Founder | F76: Stealth Start Up | G76: Games | H76: chrisokelly@gmail.com | J76: https://www.linkedin.com/in/chrisokelly/ | K76: Mattie Fairchild
A77: Christian Hübel | B77: Christian | C77: Hübel | D77: christian.huebel@gmx.net | E77: (Indie) Founder & Director | F77: One More Journey | G77: Games | H77: christian.huebel@gmx.net | J77: https://www.linkedin.com/in/huebelchristian/ | K77: Saw Grace Zhou's LinkedIn Post :)
A78: Dominik Sypnicki | D78: dominik@virtual-alchemy.games | E78: CEO | F78: Virtual Alchemy | G78: Games, VC | H78: dominik@virtual-alchemy.games | I78: 48883305506 | J78: https://www.linkedin.com/in/dominiksypnicki/ | K78: Paweł Łaskarzewski
A79: Edwin Yanarico | B79: Edwin | C79: Yanarico | D79: edayb@live.com | E79: Marketing Officer | F79: Hanze University Of Applied Sciences | G79: Others, Media | H79: EdAyb@LIVE.COM | J79: http://linkedin.com/in/edwin-yanarico | K79: Ah sorry guys! Got this link from our dutch community. Still worth the try :)
A80: Fanny Moreaux | B80: Fanny | C80: Moreaux | D80: fanny@icopartners.com | E80: Senior Communications Manager | F80: Ico Partners | G80: Media, Others, Games | H80: Fanny@icopartners.com | J80: https://www.linkedin.com/in/fannymoreaux/ | K80: I found this event through the "Gamescom 2025 Events" spreadsheet so no one really - but I've been communicating with different people of the Polygon staff each week.
A81: Florian Pabst | B81: Florian | C81: Pabst | D81: florian@gameinfluencer.com | E81: COO | F81: GameInfluencer GmbH | G81: Games | H81: florian@gameinfluencer.com | J81: https://www.linkedin.com/in/flopabst/ | K81: Georg Broxtermann
A82: Mark Nechayev | B82: Mark | C82: Nechayev | D82: gamescom@ufi-research.com | E82: Owner | F82: UFI Research | G82: Others | H82: gamescom@ufi-research.com | J82: linkedin.com/in/mnechaye | K82: Sam
A83: Gregory Andre | B83: Gregory | C83: Andre | D83: greg@doublejack.io | E83: Head of Business | F83: Double Jack | G83: Games | H83: greg@doublejack.io | J83: https://www.linkedin.com/in/greg-a-%F0%9F%94%9C-gamescom-84313230b/ | K83: Dave Shin
A84: Michael Grombach | B84: Michael | C84: Grombach | D84: grombach@magenta.de | E84: IT-Systemadministrator | F84: UFF IT & Service | G84: Infrastructure | H84: grombach@magenta.de | J84: https://www.linkedin.com/in/michael-grombach-2790a01a3?utm_source=share&utm_campaign=share_via&utm_content=profile&utm_medium=ios_app
A85: Guillaume Bouckaert | D85: guillaume.bouckaert.gd@gmail.com | E85: Administrator | F85: games.brussels | G85: Others, Games | H85: games.brussels@gmail.com | J85: https://www.linkedin.com/in/guillaume-bouckaert-a5b1a32a/ | K85: No formal invitation
A86: Huei Chan | B86: Huei | C86: Chan | D86: hc@rapideyemovers.com | E86: Producer | F86: RapidEyeMovers | G86: Game Studio | H86: hc@rapideyemovers.com | J86: https://uk.linkedin.com/in/hueichan | K86: John
A87: Heinz DuBois Vera | D87: heinzdubois@gmail.com | E87: Game Designer | F87: Inmerxia | G87: Game Studio | H87: heinzdubois@hotmail.com | I87: 51959561430 | J87: https://www.linkedin.com/in/heinzdbv/ | K87: Grace Zhou
A88: Hind Toufga | B88: Hind | C88: Toufga | D88: hinda.toufga@gmail.com | E88: BizDev | F88: Northify | G88: Others | H88: hinda.toufga@gmail.com | I88: Sverige | J88: https://www.linkedin.com/in/hind-toufga/ | K88: Devcom staff
A89: Jeet Thakkar | B89: Jeet | C89: Thakkar | D89: jeet.thakkar@lysto.io | E89: Chief Business Officer | F89: Lysto | G89: AI | H89: jeet@lysto.io | J89: https://linkedin.com/in/jeetthakkar | K89: Grace Zhou
A90: Jeff | B90: Jeff | D90: jeff@gamesmiths.co.uk | E90: Advisor | F90: WARP Publishing | G90: Infrastructure | H90: jeff@gamesmiths.co.uk | J90: https://www.linkedin.com/in/jeffpabst/ | K90: Max K
A91: Jeremy Joiner | B91: Jeremy | C91: Joiner | D91: jeremy.joiner@rocketscience.gg | E91: VP of Business Development | F91: Rocket Science | G91: Game Studio | H91: jeremy.joiner@rocketscience.gg | J91: https://www.linkedin.com/in/jeremyjoiner1/ | K91: Kendre
A92: John Kavanagh | B92: John | C92: Kavanagh | D92: john@yom.net | E92: Partnerships Director | F92: YOM | G92: Infrastructure | H92: john@yom.net | J92: https://www.linkedin.com/in/jklinkedin/ | K92: Grace Zhou
A93: Jorrit Velzeboer | B93: Jorrit | C93: Velzeboer | D93: jorrit@yom.net | E93: CEO | F93: YOM | G93: Infrastructure | H93: jorrit@yom.net | I93: https://t.me/yom_jorrit | J93: https://www.linkedin.com/in/jvelzeboer/ | K93: Grace Zhou
A94: Joseph Azzam | D94: josephazzam@hotmail.com | E94: Technical Artist | F94: Romero Games | G94: Games | H94: josephazzam@hotmail.com | J94: josephazzam | K94: Grace Zhou
A95: Julio Cesar Guedes | D95: juliocesarguedesk@gmail.com | E95: 3D Artist | F95: Cyan heart | G95: Games | H95: Juliocesarguedesk@gmail.com | J95: www.linkedin.com/in/julio-3d-prop-artist | K95: Caio Filizola
A96: Justin edwards | D96: juzzy007@gmail.com | E96: Chief Publishing Officer | F96: WARP | G96: Others, Blockchain, Game Publisher | H96: Juzzy007@gmail.com | I96: Juzzy007 | J96: https://www.linkedin.com/in/justin-edwards-876a193/ | K96: Max K
A97: Victoria Kis | B97: Victoria | C97: Kis | D97: kis@gamingpartys.de | E97: Designer & Photography | F97: gamingpartys.de | G97: Media | H97: kis@gamingpartys.de | J97: https://www.linkedin.com/in/victoria-kis-194270259/ | K97: Grace Zhou
A98: Patrick Tschorn | B98: Patrick | C98: Tschorn | D98: lavalampe@couchcoop.info | E98: Owner | F98: Couchcoop.info | G98: Media | H98: lavalampe@couchoop.info | J98: https://www.linkedin.com/in/patrick-tschorn-968106150/ | K98: Grace Zhou
A99: Max Cotin | D99: maxime.cotin@apptweak.com | E99: AE | F99: AppTweak | G99: Others | H99: maxime.cotin@apptweak.com | J99: https://www.linkedin.com/in/maximecotin/ | K99: /
A100: Michael Davies | B100: Michael | C100: Davies | D100: mdavies@usspeaking.com | E100: Sales Associate | F100: Universally Speaking | G100: Games | H100: mdavies@usspeaking.com | J100: https://www.linkedin.com/in/michael-davies-ish/ | K100: Grace Zhou
...

Sheet RSVPs - July 30
A1: name | B1: first_name | C1: last_name | D1: email | E1: approval_status | F1: Job Title | G1: Company | H1: Type of Company | I1: Email | J1: Telegram | K1: What's your LinkedIn ? | L1: Kindly provide the name of the person who invited you to this event
A2: Aria Esrafilian | B2: Aria | C2: Esrafilian | D2: aria@troverse.io | E2: approved | F2: Founder | G2: Troverse (GameFi x GenAI | x.com/PlayTroverse) | H2: AI, Blockchain, Game Studio | I2: Aria@playtroverse.com | J2: @ariaesrafilian | K2: https://linkedin.com/in/ariaesrafilian | L2: GameFi project building on Polygon
A3: Berker Siino | B3: Berker | C3: Siino | D3: berkersiino@outlook.com | E3: approved | F3: Art Director | G3: MonsterPuppet | H3: Game Studio | I3: berker@monster-puppet.com | K3: https://www.linkedin.com/in/berkersiino/ | L3: Marcus
A4: Jeremy Parris | B4: Jeremy | C4: Parris | D4: jeremy@kingriver.co | E4: approved | F4: ventures/consulting | G4: King River Capital | H4: VC, Others | I4: jeremy@kingriver.co | J4: jeremystormsky | K4: https://www.linkedin.com/in/jeremy-parris-b242a4211/ | L4: know jon raddoff and a lot of the wolves
A5: Tommaso Jakob | B5: Tommaso | C5: Jakob | D5: tommaso.jakob@ubisoft.com | E5: approved | F5: Project Coordinator - ANNO Brand | G5: Ubisoft Mainz | H5: Game Studio | I5: tommaso.jakob@ubisoft.com | K5: https://www.linkedin.com/in/tommasojakob/ | L5: Haye Anderson
A6: Kristian Metzger | D6: kristian@stratosphere-games.com | E6: approved | F6: CEO | G6: Stratosphere Games GmbH | H6: Game Studio | I6: kristian@stratosphere-games.com | J6: @Khorneslayer24 | K6: https://linkedin.com/in/kristianmetzger | L6: Max Kaufman
A7: Tim Loosen | B7: Tim | C7: Loosen | D7: tim@lussa.io | E7: approved | F7: CBO | G7: Lussa | H7: Infrastructure | I7: Info@lussa.io | J7: @Powerlauch | K7: https://www.linkedin.com/in/tim-loo?utm_source=share&utm_campaign=share_via&utm_content=profile&utm_medium=android_app | L7: Jon Radoff
A8: Zlatko Stjepanović | B8: Zlatko | C8: Stjepanović | D8: zlatko@lussa.io | E8: approved | F8: CEO | G8: Lussa | H8: Infrastructure | I8: zlatko@lussa.io | J8: @zlatko369 | K8: https://www.linkedin.com/in/zlatko-z?utm_source=share&utm_campaign=share_via&utm_content=profile&utm_medium=android_app | L8: Jon Radoff
A9: Niels de Ruiter | B9: Niels | C9: de Ruiter | D9: hello@nielsderuiter.com | E9: approved | F9: Investor | G9: notneils | H9: VC | I9: hello@nielsderuiter.com | J9: noosoods | K9: https://www.linkedin.com/in/nielsderuiter1/ | L9: Max Kaufman (web3 frens group)
A10: MinChi Park | B10: Minchi | C10: Park | D10: park.minchi@gmail.com | E10: approved | F10: Head of Ecosystem | G10: HyperPlay | H10: Infrastructure, Blockchain | I10: minchi@hyperplay.xyz | K10: https://linkedin.com/in/minchipark | L10: Max
A11: Sydney Sharp | B11: Sydney | C11: Sharp | D11: ssharp@3thix.com | E11: approved | F11: Bd | G11: 3thix | H11: Blockchain, Infrastructure, Wallet | I11: Ssharp@3thix.com | J11: Sydneysharp | K11: https://www.linkedin.com/in/sydney--sharp | L11: Max Kaufman
A12: TIMOTHY R TELLO | B12: Timothy | C12: Tello | D12: ttello@3thix.com | E12: approved | F12: CEO | G12: 3thix | H12: Blockchain, Wallet, Infrastructure | I12: Ttello@3thix.com | J12: Tellotimothy | K12: https://www.linkedin.com/in/timothytello | L12: Max Kaufman
A13: Sebastien BORGET | B13: Sebastien | C13: Borget | D13: seb@sandbox.game | E13: approved | F13: Co-Founder | G13: The Sandbox | H13: Blockchain, Game Publisher | I13: seb@sandbox.game | J13: sebastienborget | K13: https://www.linkedin.com/in/borgetsebastien | L13: Max Kaufman
A14: Thomas Rössig | B14: Thomas | C14: Rössig | D14: thomas@roessig.biz | E14: approved | F14: Founder / Fractional CEO | G14: Game Founder Coach / Playing Mantis | H14: Game Studio | I14: thomas@roessig.biz | K14: https://www.linkedin.com/in/thomasroessig/ | L14: Not invited by someone, I used to run a studio in the web3 space.
A15: Robin Squire | B15: Robin | C15: Squire | D15: robin@blackbloxk.io | E15: approved | F15: CEO | G15: Black Block | H15: Game Studio, Infrastructure | I15: robin@blackblock.io | K15: https://www.linkedin.com/in/robin-squire | L15: Max Kaufman
A16: Anton Umnov | B16: Anton | C16: Umnov | D16: anton@helika.io | E16: approved | F16: Founder and CEO | G16: Helika | H16: Infrastructure, Game Publisher | I16: Anton@helika.io | K16: https://linkedin.com/in/anton-umnov | L16: Max
A17: Nahir | B17: Nahir | D17: mizuchin12@gmail.com | E17: approved | F17: CEO | G17: Dreams of Heaven Games | H17: Game Studio | I17: Mizuchin12@gmail.com | K17: https://linkedin.com/in/nahir-fajardo | L17: None
A18: Nate Dykstra | B18: Nate | C18: Dykstra | D18: nate.dykstra@mattel.com | E18: approved | F18: Business Development, Licensing | G18: Mattel | H18: Game Publisher | I18: nate.dykstra@mattel.com | K18: https://www.linkedin.com/in/natedykstra/ | L18: Giancarlo Rios
A19: Alex Tarrand | D19: alex@styngr.com | E19: approved | F19: COO | G19: STYNGR | H19: Media | I19: alex@styngr.com | J19: @alextarrand | K19: https://www.linkedin.com/in/alextarrand/ | L19: Grace
A20: Assad Dar | D20: assad.dar@moongaming.com | E20: approved | F20: Founder & CVO | G20: Medieval Empires | H20: Game Studio | I20: Assad.dar@gmail.com | J20: @assad_dar | K20: LinkedIn.com/in/assaddar | L20: Our $MEE token is on Polygon
A21: Rufus Kubica | D21: rufus.kubica@11bitstudios.com | E21: approved | F21: External Development Director | G21: 11 bit studios | H21: Game Publisher, Game Studio | I21: rufus.kubica@11bitstudios.com | K21: https://www.linkedin.com/in/rufus-kubica-9482b7a5/ | L21: Got the invite from our PR Team
A22: Oliver Löffler | B22: Oliver | C22: Löffler | D22: oliver@voya.games | E22: approved | F22: CEO | G22: VOYA Games | H22: Game Studio, Game Publisher | I22: oliver@voya.games | K22: https://www.linkedin.com/in/oliverloeffler/ | L22: Sai
A23: Luai Mahjneh | D23: luai.mahjneh@fennicagaming.com | E23: approved | F23: SVP | G23: Fennica Gaming | H23: Game Publisher | I23: luai.mahjneh@fennicagaming.com | K23: https://www.linkedin.com/in/luaimahjneh/ | L23: Tom Jaatinen
A24: Baptiste Granet | B24: Baptiste | C24: Granet | D24: baptiste.granet@immutable.com | E24: approved | F24: BD, EMEA Manager | G24: Immutable | H24: Blockchain | I24: baptiste.granet@immutable.com | J24: baptistegrnt | K24: https://linkedin.com/in/baptiste-granet | L24: No invite, but working with Sergio and Kamil on a regular basis
A25: Rana Rahman | B25: Rana | C25: Rahman | D25: rana@raptorpr.com | E25: approved | F25: CEO & Founder | G25: Raptor PR | H25: Media | I25: Rana@raptorpr.com | J25: @ranaraptor | K25: https://linkedin.com/in/ranaraptor | L25: Max Kaufman
A26: Joshua Callaghan | B26: Joshua | C26: Callaghan | D26: joshua@raptorpr.com | E26: approved | F26: Junior Account Manager | G26: Raptor PR | H26: Others | I26: joshua@raptorpr.com | K26: https://www.linkedin.com/in/joshua-callaghan/ | L26: Max Kaufman
A27: Mike Sanders | B27: Mike | C27: Sanders | D27: msanders@punyhuman.com | E27: approved | F27: Chief Development Officer | G27: Carbonated | H27: Game Studio | I27: msanders@punyhuman.com | J27: @urinalcake | K27: https://www.linkedin.com/in/mikerobyte/ | L27: Grace Zhou
A28: Dustin Brower | B28: Dustin | C28: Brower | D28: dustin@blueravenla.com | E28: approved | F28: Head of Brand Partnerships | G28: Blue Raven | H28: Others | I28: dustin@blueravenla.com | K28: https://www.linkedin.com/in/dustinbrower/ | L28: Grace Zhou
A29: Johnny Chua | B29: Johnny | C29: Chua | D29: johnny@lightningforge.games | E29: approved | F29: CCO | G29: Lightning Forge Games | H29: Game Studio, Blockchain | I29: johnny@lightningforge.games | J29: @Hit_Box_01 | K29: https://linkedin.com/in/jonathanjchua | L29: Max Kaufman
A30: Sean Shin | B30: Sean | C30: Shin | D30: seanshin@com2us.com | E30: approved | F30: Global BD Lead | G30: Com2uS Platform | H30: Game Studio | I30: seanshin@com2us.com | K30: https://www.linkedin.com/in/seonhoshin/ | L30: -
A31: Sky | B31: Sky | D31: sky@wolvesdao.io | E31: approved | F31: CTO | G31: Woof labs | H31: Others | I31: sky@wolvesdao.io | K31: https://www.linkedin.com/in/jonathan-bruenderman-4ba5151b/ | L31: Payton Kaleiwahea
A32: Serhat MARASLIGIL | B32: Serhat | C32: Marasligil | D32: smar@sequence.xyz | E32: approved | F32: Senior Producer | G32: Sequence | H32: Blockchain, Infrastructure, Wallet | I32: Smar@sequence.xyz | J32: Themarasligil | K32: https://www.linkedin.com/in/serhatmarasligil?utm_source=share&utm_campaign=share_via&utm_content=profile | L32: Max Kaufman
A33: Brian McWilliams | D33: brian@wildblueberrygames.com | E33: approved | F33: CEO | G33: Wild Blueberry Games | H33: Game Studio | I33: brian@wildblueberrygames.com | J33: @BrianMcWilliams | K33: https://www.linkedin.com/in/brian-mcwilliams-b68b63b8/ | L33: Michael Sanders shared the event with me
A34: Saad Zaeem | B34: Saad | C34: Zaeem | D34: saad@revolvinggames.com | E34: approved | F34: CEO | G34: Revolving Games | H34: Game Publisher | I34: saad@revolvinggames.com | K34: https://linkedin.com/in/saadzaeem | L34: Shreyansh
A35: Eujin OH | B35: Eujin | C35: Oh | D35: eujin@com2us.com | E35: approved | F35: Marketing Manager | G35: Com2us Platform | H35: Game Publisher, Game Studio, Infrastructure | I35: eujin@gmail.com | K35: https://www.linkedin.com/in/eujinoh/ | L35: Sunho Shin
A36: Clementine AH-GON | B36: Clementine | C36: Ah-Gon | D36: clementine.ah-hon@ubisoft.com | E36: approved | F36: Junior International Product Manager | G36: Ubisoft Mainz | H36: Game Studio | I36: clementine.ah-hon@ubisoft.com | K36: https://www.linkedin.com/in/clementine-ah-hon/ | L36: Haye Anderson
A37: David An | B37: David | C37: An | D37: david@dracoon.ventures | E37: approved | F37: Managing Partner | G37: Dracoon Ventures | H37: VC, Blockchain | I37: david@dracoon.ventures | J37: davidkendo | K37: https://linkedin.com/in/davidan | L37: BGA
A38: Mel | B38: Mel | C38: Dow | D38: melanie@blockchaingamealliance.net | E38: approved | F38: Comms and BD | G38: Blockchain Game Alliance | H38: Blockchain | I38: Melanie@blockchaingamealliance.net | K38: https://linkedin.com/in/melanie-dow | L38: Sergio
A39: Gabriela Siemienkowicz | B39: Gabriela | C39: Siemienkowicz | D39: gabriela.siemienkowicz@11bitstudios.com | E39: approved | F39: Communications Lead | G39: 11 Bit Studios | H39: Game Publisher, Game Studio | I39: gabriela.siemienkowicz@11bitstudios.com | J39: Poland | K39: https://www.linkedin.com/in/gabriela-siemienkowicz/ | L39: Jason Ying
A40: Laurens | B40: Laurens | C40: Lauwverse | D40: lamastijgen@gmail.com | E40: approved | F40: CPO | G40: WolvesDAO | H40: Media | I40: Lauw@wolvesdao.io | K40: http://linkedin.com/in/laurensverweij | L40: Wolvesdao
A41: Gabriel Stürmer | D41: gabriel@clapclap.games | E41: approved | F41: CEO | G41: 👏 Clap 👏 Clap Games | H41: Game Publisher | I41: gabriel@clapclap.games | K41: https://www.linkedin.com/in/gabrielsturmer/ | L41: --
A42: Daniel Bowen | B42: Daniel | C42: Bowen | D42: dan.bowen@stash.gg | E42: approved | F42: Growth Lead | G42: Stash | H42: Others | I42: Dan.bowen@stash.gg | K42: https://www.linkedin.com/in/daniel-bowen-?utm_source=share&utm_campaign=share_via&utm_content=profile&utm_medium=ios_app | L42: Max Kaufman
A43: Anthony Cain | D43: acain@teamliquid.com | E43: approved | F43: Head of Agency, Liquid Media | G43: Team Liquid | H43: Media | I43: acain@teamliquid.com | K43: http://www.linkedin.com/in/socialcain | L43: N/A
A44: Metavert | Jon Radoff | B44: Jon | C44: Radoff | D44: jon@beamable.com | E44: approved | F44: CEO | G44: Beamable | H44: Infrastructure | I44: jon@beamable.com | J44: @jradoff | K44: https://www.linkedin.com/in/jonradoff/ | L44: Beamable (we are hosting)
A45: Trapper Markelz | B45: Trapper | C45: Markelz | D45: trapper@beamable.com | E45: approved | F45: COO | G45: Beamable | H45: Infrastructure | I45: trapper@beamable.com | J45: @trappermarkelz | K45: https://www.linkedin.com/in/trappermarkelz/ | L45: Beamable (we are hosting)
A46: Ali El Rhermoul | D46: ali@beamable.com | E46: approved | F46: CTO | G46: Beamable | H46: Infrastructure | I46: ali@beamable.com | J46: @aelrhermoul | K46: https://www.linkedin.com/in/aelrhermoul/ | L46: Beamable (we are hosting)
A47: Jon Radoff | B47: Jon | C47: Radoff | D47: ryan@beamable.com | E47: approved | F47: Executive Assistant / Chief of Staff | G47: Beamable | H47: Infrastructure | I47: ryan@beamable.com | J47: @RMackeen | K47: https://www.linkedin.com/in/ryanmackeen/ | L47: Beamable (we are hosting)
A48: Ilya Abugov | B48: Ilya | C48: Abugov | D48: ilya@helika.io | E48: approved | F48: director of ventures | G48: Helika | H48: Others | I48: ilya@helika.io | J48: ilabugov | K48: https://www.linkedin.com/in/ilya-abugov/ | L48: found the event on lu.ma
A49: Serkan Akdeniz | B49: Serkan | C49: Akdeniz | D49: serkan@vloot.io | E49: approved | F49: COO | Founder | Founder | G49: CSGold.gg | vLoot.io | hade.gg | H49: iGaming, Media | I49: serkan@vloot.io | J49: @serkan | K49: https://www.linkedin.com/in/serkan-akdeniz-%E2%9E%A1%EF%B8%8F-iem-cologne-gamescom-887258185/ | L49: Max Kaufman
A50: Immutable | D50: hannah.blane@immutable.com | E50: approved | F50: Events | G50: Immutable | H50: Game Publisher | I50: hannah.blane@immutable.com | J50: han_blane | K50: https://www.linkedin.com/in/hannah-blane/ | L50: Blake Polygon
A51: Amanda | B51: Amanda | D51: amanda.shih@gameloft.com | E51: approved | F51: Business Developer | G51: Gameloft | H51: Game Publisher | I51: amanda.shih@gameloft.com | K51: www.linkedin.com/in/shihamanda | L51: Gamescom side event
A52: Victor Vielliard | B52: Victor | C52: Vielliard | D52: victor.v@tap-nation.io | E52: approved | F52: Head of M&A | G52: Tapnation | H52: Game Publisher | I52: victor.v@tap-nation.io | K52: https://www.linkedin.com/in/victor-vielliard-partnerships/ | L52: Kamil Zielinski
A53: Çoruh Şimşek | B53: Çoruh | C53: Şimşek | D53: coruhsimsek@gmail.com | E53: approved | F53: CEO | G53: CogniScope | H53: AI | I53: coruh@cogniscope.co | K53: https://linkedin.com/in/coruhsimsek | L53: Osman Sarman
A54: Diana S | B54: Диана | C54: Сафина | D54: j9wj8sk64v@privaterelay.appleid.com | E54: approved | F54: CBO | G54: Algebras AI | H54: AI | I54: Diana@algebras.ai | J54: Diswana | K54: https://linkedin.com/in/diana-safina | L54: Max Kaufman
A55: Aira Mongush | B55: Aira | C55: Mongush | D55: aira@algebras.ai | E55: approved | F55: CEO & Founder | G55: Algebras AI | H55: AI | I55: aira@algebras.ai | J55: @aira_mo | K55: https://linkedin.com/in/aira-mongush | L55: Max Kauffman
A56: omer behar | B56: Omer | C56: Behar | D56: omer@rabbitholecreations.studio | E56: approved | F56: CEO | G56: Rabbit Hole Creations | H56: Game Studio | I56: omer@rabbitholecreations.studio | K56: https://www.linkedin.com/in/omer-behar/ | L56: David
A57: Eva Ramirez | B57: Eva | C57: Ramirez | D57: eva@beamable.com | E57: approved | F57: Head of Customer Success | G57: Beamable | H57: Infrastructure | I57: Eva@Beamable.com | J57: NA | K57: https://www.linkedin.com/in/evamramirez/ | L57: Beamable (we are hosting)
A58: Sam Pottinge | B58: Sam | C58: Pottinge | D58: sam@carry1st.com | E58: approved | F58: Business Development Lead | G58: Carry1st | H58: Game Publisher, Infrastructure, Media, Game Studio | I58: sam@carry1st.com | K58: https://www.linkedin.com/in/sam-pottinger/ | L58: Andrew Rowland
A59: Eliana Russi | D59: eliana.russi@gamescom.com.br | E59: approved | F59: Chief Programming Officer | G59: gamescom latam | H59: Others | I59: eliana.russi@gamescom.com.br | K59: https://www.linkedin.com/in/eliana-russi-🔜-devcom-gamescom-b447979 | L59: Max Kaufman
A60: Winston Esposito | D60: winston@modl.ai | E60: approved | F60: CEO | G60: modl.ai | H60: Infrastructure | I60: winston@modl.ai | K60: https://www.linkedin.com/in/winston-esposito-79498134/ | L60: Ferhan Ozkan
A61: Garrison Bellack | B61: Garrison | C61: Bellack | D61: g@playdreamworld.com | E61: approved | F61: CEO and Co-founder | G61: DreamWorld | H61: AI, Game Studio | I61: g@playdreamworld.com | J61: Garrison_Bellack | K61: https://linkedin.com/in/garrisonbellack | L61: Max Kaufman
A62: Irena Pereira | B62: Irena | C62: Pereira | D62: irena@infiniterealms.com | E62: approved | F62: CEO | G62: Infinite Realms | H62: Infrastructure | I62: irena@infiniterealms.com | K62: http://www.linkedin.com/in/irenapereira | L62: Max Kaufman
A63: Lee Seung Hee | D63: seunghee@liquidx.studio | E63: approved | F63: Head of Product | G63: Pixelmon | H63: Game Publisher | I63: seunghee@liquidx.studio | K63: https://www.linkedin.com/in/seung-hee-lee-3488b894/ | L63: Max
A64: Asi Burak | D64: aburak@tiltingpoint.com | E64: approved | F64: CBO | G64: Tilting Point | H64: Games | I64: aburak@tiltingpoint.com | K64: https://www.linkedin.com/in/asiburak/ | L64: Marina Espin
A65: Alex Crawford | B65: Alex | C65: Crawford | D65: alex.crawford@immutable.com | E65: approved | F65: Enterprise BDM | G65: Immutable | H65: Blockchain | I65: alex.crawford@immutable.com | J65: @alex_crawf | K65: https://www.linkedin.com/in/alexcrawfordau/ | L65: Sergio / Kamil
A66: Anna Kuzmenko | B66: Anna | C66: Kuzmenko | D66: anna.kuzmenko@immutable.com | E66: approved | F66: BD Manager APAC | G66: Immutable | H66: Games | I66: anna.kuzmenko@immutable.com | J66: immutanna | K66: https://linkedin.com/in/anna-kuzmenko | L66: Immutable team
A67: Antonio Guaranys | D67: antonio.guaranys@hermitcrabstudio.com | E67: approved | F67: Business Developer | G67: Hermit Crab | H67: Game Studio | I67: antonio.guaranys@hermitcrabstudio.com | K67: www.linkedin.com/in/antonioguaranys | L67: Trapper
A68: Ataberk Ates | B68: Ataberk | C68: Ates | D68: ataberk@ataberkates.com | E68: approved | F68: Lead Designer | G68: Climax Studios | H68: Game Studio | I68: ataberk@ataberkates.com | K68: https://www.linkedin.com/in/ataberkates/ | L68: -
A69: Polygon Labs | B69: Blake | C69: Payne | D69: bpayne@polygon.technology | E69: approved | F69: Manager | G69: Polygon | H69: Infrastructure | I69: bpayne@polygon.technology | K69: https://linkedin.com/in/blakefpayne | L69: Max
A70: Bret Curan | B70: Bret | C70: Curan | D70: bret@lightningforge.games | E70: approved | F70: Chief Product Officer / Co-founder | G70: Lightning Forge Games | H70: AI, Game Studio | I70: bret@lightningforge.games | J70: @BusinessCatAU | K70: https://linkedin.com/in/bret-curan-092b82256 | L70: Max Kaufman
A71: Caio Filizola | B71: Caio | C71: Filizola | D71: caiofilizola@cyanheartstudio.com | E71: approved | F71: CEO | G71: Cyan Heart Studio | H71: Games | I71: caiofilizola@cyanheartstudio.com | K71: https://www.linkedin.com/in/caio-filizola/ | L71: N/A
A72: chris castagnetto | B72: Chris | C72: Castagnetto | D72: ccas121@gmail.com | E72: approved | F72: Business Development | G72: TikTok | H72: Others | I72: ccas121@gmail.com | K72: https://www.linkedin.com/in/ccastagnetto/ | L72: web list
A73: Cecilia | D73: cecilia.fadul@kwalee.com | E73: approved | F73: Head of AdMonetisation | G73: Kwalee | H73: Games | I73: cecilia.fadul@kwalee.com | K73: https://www.linkedin.com/in/ceciliafadul/ | L73: slack
A74: Romain Schneider | B74: Romain | C74: Schneider | D74: ceo@spectarium.games | E74: approved | F74: CEO and Founder | G74: Spectarium Games | H74: Games | I74: Ceo@spectarium.games | K74: linkedin.com/in/rdgs15 | L74: Sam, WolvesDAO
A75: Chris Keeling | D75: chris@marsgames.com | E75: approved | F75: CEO | G75: Mars Games | H75: Games | I75: chris@marsgames.com | K75: https://www.linkedin.com/in/chriskeeling/ | L75: Mattie Fairchild
A76: Ciaran Daly | D76: ciaran.daly@twistedworks.com | E76: approved | F76: Director | G76: Twisted Works | H76: Games, Media | I76: ciaran.daly@twistedworks.com | K76: https://www.linkedin.com/in/ciarandaly/ | L76: N/A
A77: David Boileau | B77: David | C77: Boileau | D77: dave.boileau@gamebreaking.com | E77: approved | F77: Senior Engineering Manager | G77: Gamebreaking Studios | H77: Game Studio | I77: dave.boileau@gamebreaking.com | K77: https://www.linkedin.com/in/davidboileau/ | L77: Grace Zhou
A78: Diego Beltrame | B78: Diego | C78: Beltrame | D78: diego.beltrame@unity3d.com | E78: approved | F78: Sr Client Partner | G78: Unity Multiplay | H78: Infrastructure | I78: diego.beltrame@unity3d.com | K78: https://www.linkedin.com/in/beltramediego/ | L78: working with Web3 customers
A79: Elena Provine | B79: Elena | C79: Provine | D79: elena@equitywestadvisors.com | E79: approved | F79: Venture Partner | G79: Griffin Gaming | H79: VC | I79: elena@equitywestadvisors.com | J79: lena_provine | K79: https://www.linkedin.com/in/elenaprovine/ | L79: Greg Labuz
A80: flavia | B80: Flavia | D80: flavia.luz@webcore.com.br | E80: approved | F80: Operations | G80: Webcore Games | H80: Games | I80: flavia.luz@webcore.com.br | J80: 5511992077151 | K80: https://www.linkedin.com/in/flavialuz/ | L80: Grace Zhou
A81: Fred @ Funfair Ventures | B81: Fred | D81: frederico.kessler@funfair.io | E81: approved | F81: Partner | G81: Funfair ventures | H81: VC | I81: Frederico.kessler@funfair.io | J81: Fr3dsk | K81: https://linkedin.com/in/fr3dk | L81: Found it on luma
A82: GaspodeWD // Felix | B82: Felix | C82: Bracher | D82: gaspodewd@whatsyourgam3.com | E82: approved | F82: CSO // Head Of Marketing | G82: FDF // G3 | H82: Media | I82: gaspodewd@whatsyourgam3.com | K82: https://www.linkedin.com/in/felix-bracher/ | L82: Big Dog Max
A83: Georg Broxtermann | B83: Georg | C83: Broxtermann | D83: georg@gameinfluencer.com | E83: approved | F83: CEO | G83: GameInfluencer.com | H83: Media | I83: georg@gameinfluencer.com | K83: https://linkedin.com/in/broxtermann | L83: Sergio Varona Bustillo
A84: Grace Zhou | B84: Grace | C84: Zhou | D84: gracemin.zhou@gmail.com | E84: approved | F84: Director of Corp Dev | G84: Scopely | H84: Games | I84: grace.zhou@scopely.com | K84: https://linkedin.com/in/graceminzhou | L84: Polygon
A85: Gunjan Sharman | B85: Gunjan | C85: Sharman | D85: gunjan@beamable.com | E85: approved | F85: VP of Product | G85: Beamable | H85: Infrastructure | I85: gunjan@beamable.com | J85: i_gsharman | K85: https://linkedin.com/in/gsharman | L85: Max Kauffman
A86: Haye Anderson | B86: Haye | C86: Anderson | D86: haye.anderson@ubisoft.com | E86: approved | F86: Brand Director | G86: Ubisoft | H86: Game Studio | I86: Haye.anderson@ubisoft.com | K86: https://www.linkedin.com/in/andersonhayley/ | L86: Alex Brodsky
A87: Marcus Krautwurst | B87: Marcus | C87: Krautwurst | D87: hello@monster-puppet.com | E87: approved | F87: CEO | G87: Monster Puppet Corporation | H87: Games | I87: hello@monster-puppet.com | K87: https://www.linkedin.com/in/mkrautwurst?utm_source=share&utm_campaign=share_via&utm_content=profile&utm_medium=ios_app | L87: Hind
A88: Jan Roessner | B88: Jan | C88: Roessner | D88: jan@oneearthrising.com | E88: approved | F88: CEO | G88: One Earth Rising | H88: Infrastructure | I88: jan@oneearthrising.com | J88: @janroessner | K88: https://linkedin.com/in/janroessner | L88: Max Kaufman
A89: Joachim Rittfeldt Hofvenschiöld | B89: Joachim | C89: Rittfeldt Hofvenschiöld | D89: joachim@spectarium.games | E89: approved | F89: BD / Investor | G89: Spectarium Games / uBIT.vc | H89: Games, VC | I89: Joachim@ubit.vc | J89: Hofvenschiold | K89: Linkedin.com/in/hofven | L89: Sam, WolvesDAO
A90: John Bergman | D90: john@guildsoftware.com | E90: approved | F90: CEO | G90: Guild Software | H90: Game Studio, Game Publisher | I90: john@guildsoftware.com | J90: @JohnBergman | K90: linkedin.com/in/incarnate | L90: Grace Zhou's secret telegram thing. We have a live MMORPG with substantial users, considering possible blockchain partners.
A91: Justin Edwards | B91: Justin | C91: Edwards | D91: justin@twintec.io | E91: approved | F91: CPO | G91: WARP | H91: Game Publisher, Infrastructure, Blockchain | I91: Justin@twintec.io | J91: Juzzy007 | K91: https://www.linkedin.com/in/justin-edwards-876a193/ | L91: Matthew Buxton
A92: Kate Edwards | D92: kate@geogrify.com | E92: approved | F92: CEO / CXO & Cofounder | G92: Geogrify / SetJetters | H92: Others | I92: kate@geogrify.com | K92: https://www.linkedin.com/in/geogrify/ | L92: Hind Toufga
A93: Keith Flynn | B93: Keith | C93: Flynn | D93: keith.flynn@finoa.io | E93: approved | F93: Sr. Sales / Partnerships Manager | G93: Finoa | H93: Exchange, AI, Infrastructure | I93: keith.flynn@finoa.io | J93: @F_Keith | K93: https://www.linkedin.com/in/keith-flynn-/ | L93: Max via Jeremy Parris & Sonny Tsiopani
A94: Konrad Adamczewski | D94: konrad.adamczewski@11bitstudios.com | E94: approved | F94: Senior PR Manager | G94: 11 bit studios | H94: Game Publisher, Game Studio | I94: konrad.adamczewski@11bitstudios.com | K94: www.linkedin.com/in/konrad-adamczewski-292a26141 | L94: I just got a link from the list of events, honestly, so no direct person, unfortunately.
A95: Kristian | B95: Kristian | C95: Kolvek | D95: kristian@1minus1.com | E95: approved | F95: BD Manager at 1minus1 & BD Games Voice on Linkedin | G95: 1minus1 | H95: Others | I95: kristian@1minus1.com | K95: https://www.linkedin.com/in/kristiankolvek/ | L95: none
A96: Kevin Rubio | B96: Kevin | C96: Rubio | D96: krubio@tiltingpoint.com | E96: approved | F96: Director, Business Development | G96: Tilting Point | H96: Games | I96: krubio@tiltingpoint.com | K96: https://www.linkedin.com/in/kevin-rubio-ramirez/ | L96: Marina
A97: Krystian Jaroszynski | B97: Krystian | C97: Jaroszynski | D97: krystian@heroic.gg | E97: approved | F97: Chief commercial officer | G97: Heroic AS | H97: Others, Games | I97: krystian@heroic.gg | K97: www.linkedin.com/in/krystian-jaroszynski-80949437 | L97: Grace Zhou
A98: Kamil Zielinski | B98: Kamil | C98: Zielinski | D98: kzielinski@polygon.technology | E98: approved | F98: BD, Gaming | G98: Polygon Labs | H98: Blockchain, Games, Defi, Infrastructure | I98: kzielinski@polygon.technology | K98: www.linkedin.com/in/kzielinski94/ | L98: Sergio Varona, Max Kaufman, Blake Fuller
A99: Lisa-Maria Wittmann | B99: Lisa-Maria | C99: Wittmann | D99: lisa-maria.wittmann@ubisoft.com | E99: approved | F99: International Product Manager | G99: Ubisoft Mainz | H99: Game Studio | I99: lisa-maria.wittmann@ubisoft.com | K99: https://www.linkedin.com/in/lisamariawittmann/ | L99: Haye Anderson (Brand Director for Anno at Ubisoft Mainz)
A100: Marina | D100: marina@tiltingpoint.com | E100: approved | F100: VP of BD | G100: Tilting Point | H100: Games | I100: marina@tiltingpoint.com | K100: mespinfarran | L100: Sergio
...

Sheet RSVPs - Aug 6
A1: name | B1: first_name | C1: last_name | D1: email | E1: approval_status | F1: Job Title | G1: Company | H1: Type of Company | I1: Email | J1: Telegram | K1: What's your LinkedIn ? | L1: Kindly provide the name of the person who invited you to this event
A2: Jakub Vambersky | B2: Jakub | C2: Vambersky | D2: jvambersky@madfingergames.com | E2: approved | F2: Lead Community Manager | G2: MADFINGER Games | H2: Game Studio | I2: jvambersky@madfingergames.com | K2: https://www.linkedin.com/in/jakub-vambersky-%F0%9F%94%9C-gamescom-99179312b/ | L2: Dominik Jícha
A3: Oliver Warren | B3: Oliver | C3: Warren | D3: ollie.warren@unity3d.com | E3: approved | F3: Senior Solution Architect | G3: Unity | H3: Infrastructure | I3: ollie.warren@unity3d.com | K3: https://www.linkedin.com/in/ollie-warren-080306143/ | L3: Diego Beltrame
A4: Philippe Robert | B4: Philippe | C4: Robert | D4: philippe@tarokai.com | E4: approved | F4: CEO | G4: Tarokai | H4: Game Studio | I4: philippe@tarokai.com | K4: https://www.linkedin.com/in/philippe-robert-peachfarmer/ | L4: Baptiste Granet
A5: Lucie Colin | B5: Lucie | C5: Colin | D5: contact@tarokai.com | E5: approved | F5: COO | G5: tarokai | H5: Game Studio | I5: contact@tarokai.com | K5: https://www.linkedin.com/in/luciecolinrobert/ | L5: Baptiste granet
A6: funza | B6: funza | D6: funza15@gmail.com | E6: approved | F6: Customer Suport | G6: MADFINGER games | H6: Game Studio | I6: funza15@gmail.com | K6: https://www.linkedin.com/in/jan-nechvatal/ | L6: Dominik Jicha
A7: Dominik Jícha | B7: Dominik | C7: Jícha | D7: djicha@madfingergames.com | E7: approved | F7: Marketing Director | G7: MADFINGER Games, a.s. | H7: Game Publisher, Game Studio | I7: djicha@madfingergames.com | K7: https://www.linkedin.com/in/dominikjicha/ | L7: Found myself
A8: Hannibal Soares | B8: Hannibal | C8: Soares | D8: hannibal@boomland.io | E8: approved | F8: CEO | G8: BoomLand | Web3 Game Publishing | H8: Game Publisher | I8: Hannibal@boomland.io | K8: https://linkedin.com/in/hannibalsoares | L8: Max Kaufman
A9: Vitalii Vashchuk | B9: Vitalii | C9: Vashchuk | D9: vitalii@vashchuk.org | E9: approved | F9: Vice President, Global Head of Gaming | G9: EPAM | H9: Infrastructure, AI | I9: vitalii_vashchuk@epam.com | J9: vit.vas1 | K9: https://linkedin.com/in/vashchukvitalii | L9: Grace Zhou or use Jon Radoff
A10: Jas Singh | B10: Jas | C10: Singh | D10: jas@lightningforge.games | E10: approved | F10: Head of Marketing | G10: Lightning Forge Games | H10: Game Studio | I10: jas@lightningforge.games | J10: brains_ct | K10: https://www.linkedin.com/in/jasvir-singh-06119b1b7/ | L10: Max Kaufman
A11: Long Chu | B11: Long | C11: Chu | D11: long@ggwp.com | E11: approved | F11: VP Ops | G11: GGWP | H11: AI | I11: long@ggwp.com | K11: https://www.linkedin.com/in/longchu88/ | L11: Joi Podgorny
A12: Kathleen Sherman | B12: Kathleen | C12: Sherman | D12: kathleen.sherman@lysto.io | E12: approved | F12: Senior Game Partnerships Manager at Lysto | G12: Lysto | H12: Others | I12: kathleen.sherman@lysto.io | K12: https://www.linkedin.com/in/kathleen-sherman/ | L12: n/a
A13: Travis Anderson | B13: Travis | C13: Anderson | D13: t.anderson@xsolla.com | E13: approved | F13: Head of Developer Partnerships | G13: Xsolla | H13: Infrastructure, Blockchain, Game Publisher, VC | I13: t.anderson@xsolla.com | K13: https://www.linkedin.com/in/travisandersonpro/ | L13: Sanket Shah
A14: Andrew Willson | B14: Andrew | C14: Willson | D14: andrew@makersfund.com | E14: approved | F14: General Partner | G14: Makers Fund | H14: VC | I14: andrew@makersfund.com | K14: https://linkedin.com/in/andrewjswillson | L14: Polygon team
A15: Sergei Vasiuk | B15: Sergei | C15: Vasiuk | D15: sergei@vasi.uk | E15: approved | F15: Product Director | G15: Wargaming | H15: Game Studio, Game Publisher | I15: sergei@vasi.uk | K15: https://www.linkedin.com/in/sergeivasjuk/ | L15: Grace Zhou
A16: JOI PODGORNY from GGWP | B16: Joi | C16: Podgorny | D16: joi@ggwp.com | E16: approved | F16: Marketing & Partnerships | G16: GGWP | H16: Infrastructure | I16: joi@ggwp.com | K16: https://linkedin.com/in/joipodgorny | L16: Event list
A17: Cvetan Rusimov | B17: Cvetan | C17: Rusimov | D17: rusimov@imperiaonline.org | E17: approved | F17: CEO | G17: Imperia Online JSC | H17: Game Studio, Game Publisher | I17: rusimov@imperiaonline.org | K17: https://www.linkedin.com/in/rusimov/ | L17: Erica
A18: Laurin Bylica | B18: Laurin | C18: Bylica | D18: lb@n8.capital | E18: approved | F18: Co-founder | G18: n8 Capital | H18: VC | I18: lb@n8.capital | J18: laurin_byl | K18: https://linkedin.com/in/laurin-bylica | L18: Tim
A19: DANIEL FERNANDEZ | B19: Daniel | C19: Fernandez | D19: daniel.fernandez@ninjugames.com | E19: approved | F19: CEO | G19: NINJU GAMES | H19: Game Studio, Blockchain | I19: gamescom@ninjugames.com | K19: https://www.linkedin.com/in/mutantdani/ | L19: Continuum World developers
A20: Antonio de la Torre | B20: Antonio | C20: de la Torre | D20: sasori@ninjugames.com | E20: approved | F20: CTO | G20: Ninju Games | H20: Game Studio | I20: sasori@ninjugames.com | K20: https://www.linkedin.com/in/sasori-olkof | L20: Ninju games is the developer of continuum world, based on polygon network
A21: Stan Fiedor | B21: Stan | C21: Fiedor | D21: stan@wemade.com | E21: approved | F21: GM Europe | G21: WEMADE | H21: Game Publisher, Blockchain | I21: Stan@wemade.com | J21: @stanfiedor | K21: https://www.linkedin.com/in/sfiedor?utm_source=share&utm_campaign=share_via&utm_content=profile&utm_medium=ios_app | L21: Jon
A22: Amy | B22: Amy | D22: amxwhite@twitch.tv | E22: approved | F22: communications director | G22: Twitch, Amazon | H22: Others | I22: amxwhite@twitch.tv | K22: https://www.linkedin.com/in/amy-white1/ | L22: Dan Clancy - Twitch CEO
A23: Behfar | B23: Behfar | C23: Iranmanesh | D23: behfar@chronogames.net | E23: approved | F23: CEO | G23: Chrono Games | H23: Game Studio, AI | I23: behfar@chronogames.net | J23: behfar | K23: https://linkedin.com/in/behfar-iranmanesh-3223a6154 | L23: Gaspode (felix)
A24: Cointelegraph | B24: Maria | C24: A Schaefer | D24: maria.a@cointelegraph.com | E24: approved | F24: Events Lead | G24: Cointelegraph, Maria A | H24: Media | I24: maria.a@cointelegraph.com | J24: MaryAbb | K24: https://linkedin.com/company/cointelegraph | L24: NA
A25: chris castagnetto | D25: chris.castagnetto@bytedance.com | E25: approved | F25: Business Development | G25: TikTok | H25: Others | I25: chris.castagnetto@bytedance.com | K25: https://www.linkedin.com/in/ccastagnetto/ | L25: web list
A26: Jongmoon Kim | B26: Jongmoon | C26: Kim | D26: jongmoonkim@com2us.com | E26: approved | F26: Senior Vice President | G26: Com2uS Platform | H26: Game Publisher | I26: jongmoonkim@com2us.com | K26: https://www.linkedin.com/in/jong-moon-k-32481979/ | L26: -
A27: Tyrus Taylor | B27: Tyrus | C27: Taylor | D27: tyrus.taylor@immutable.com | E27: approved | F27: Senior BD Manager | G27: Immutable | H27: Blockchain | I27: tyrus.taylor@immutable.com | K27: https://www.linkedin.com/in/tyrus-taylor-b18567121/ | L27: Web3 Frens TG / Payton
A28: Hajar Noreddine | B28: Hajar | C28: Noreddine | D28: hajar@zbdpay.com | E28: approved | F28: VP of Business Development | G28: ZBD | H28: Wallet, Blockchain | I28: hajar@zbdpay.com | K28: https://www.linkedin.com/in/hajar-noreddine/ | L28: N/A
A29: Matt Daly | B29: Matt | C29: Daly | D29: howdy@mattda.ly | E29: approved | F29: Founder | G29: Banana Foundry | H29: Blockchain, Game Studio | I29: Matt@chaincraft.games | J29: Bliargh | K29: https://linkedin.com/in/dalymatt | L29: Elena Provine
A30: Anton Vinogradov | D30: anton@samustai.com | E30: approved | F30: Director | G30: Samustai LTD | H30: Game Publisher, Game Studio | I30: anton@samustai.com | J30: @comrademozes | K30: https://www.linkedin.com/in/mimozes/ | L30: My colleagues from publishing chat offered to meet there
A31: shahar sosa | B31: Shahar | C31: Sosa | D31: sh.sosa@gmail.com | E31: approved | F31: Co founder | G31: Rabbit hole creations | H31: Game Studio | I31: sh.sosa@gmail.com | K31: https://www.linkedin.com/in/shahar-emanuel-sosa-72b5b71a6/ | L31: David
A32: Jin Y. Bae | B32: Jin | C32: Bae | D32: jin@opengamefoundation.org | E32: approved | F32: Executive Director | G32: Opengame Foundation(CROSS) & NEXUS(Dev Co) | H32: Blockchain | I32: jin@opengamafoundation.org | K32: https://www.linkedin.com/in/jin-yeongjin-bae-40b75515/ | L32: Sebastien (sangboxgame)
A33: Thomas Shim | B33: Thomas | C33: Shim | D33: tshim@to.nexus | E33: approved | F33: Head of Global Business | G33: NEXUS | H33: Blockchain, Others | I33: tshim@to.nexus | J33: @tshim15 | K33: https://www.linkedin.com/in/thomasshim | L33: Sebastien BORGET
A34: Daniel Wilén | D34: daniel.wilen@arcticgame.se | E34: approved | F34: Managing Director | G34: Arctic Game | H34: Others | I34: daniel.wilen@arcticgame.se | J34: Sverige | K34: https://www.linkedin.com/in/danielwilen/ | L34: Pontus Mahler
A35: Arne Peters | B35: Arne | C35: Peters | D35: arne@metaverseme.io | E35: approved | F35: Co-Founder | G35: MetaverseME | H35: Infrastructure, Game Publisher, Game Studio | I35: arne@metaverseme.io | K35: https://www.linkedin.com/in/arnepeters/ | L35: Max Kaufman
A36: SEOKJIN YONG | B36: Seokjin | C36: Yong | D36: seokinyong@com2us.com | E36: approved | F36: Hive SDK Solutions Archtect team, Assistant Manager | G36: Com2uS Platform Corp | H36: Game Publisher | I36: seokjinyong@com2us.com | K36: www.linkedin.com/in/ seokjinyong-b5a961378 | L36: David Mohr
A37: Robert Huynh | B37: Robert | C37: Huynh | D37: robert@reforgedlabs.com | E37: approved | F37: Co-Founder & CEO | G37: Reforged Labs | H37: AI | I37: robert@reforgedlabs.com | K37: https://linkedin.com/in/huynhrobert | L37: Mihailo
A38: Joanie Kraut | D38: joanie@getwigi.com | E38: approved | F38: CEO | G38: Women in Games International | H38: Others, Infrastructure | I38: Joanie@getwigi.com | K38: https://www.linkedin.com/in/joanie-kraut?utm_source=share&utm_campaign=share_via&utm_content=profile&utm_medium=ios_app | L38: Max Kaufman
A39: Höskuldur Sigurðarson | D39: hoskuldur@polarregiongames.com | E39: approved | F39: Founder/CEO | G39: Polar Region Games | H39: Game Studio | I39: hoskuldur@polarregiongames.com | K39: https://www.linkedin.com/in/hoskuldurs/ | L39: From list of Grace Zhou
A40: Arsen Chatalian | B40: Arsen | C40: Chatalian | D40: arsen@astrocat.co | E40: approved | F40: Chief Operating Officer | G40: Astro Cat | H40: Game Studio | I40: arsen@astrocat.co | K40: https://www.linkedin.com/in/chatalian/ | L40: I have been working with Beamable on Star Trek Timelines for the past 5 years (at TiltingPoint and CEO of High Ground). Thought it would be nice to meet the Beamable team in person.
A41: Ian Kuznicki | B41: Ian | C41: Kuznicki | D41: iankuz25@gmail.com | E41: approved | F41: Game Programmer | G41: Overcoffeed Games | H41: Game Studio | I41: iankuz25@gmail.com | J41: @ian1kuz | K41: https://www.linkedin.com/in/ian-kuznicki/ | L41: Ignacio
A42: John Chasoulidis Abela | B42: John | C42: Chasoulidis Abela | D42: john@metaverseme.io | E42: approved | F42: Head of Studio | G42: MetaverseME | H42: Infrastructure, Game Publisher, Game Studio, Wallet, Others | I42: john@metaverseme.io | K42: https://www.linkedin.com/in/johnhasou/ | L42: Max Kaufman
A43: Jennifer Sharp | D43: jennifer.sharp@paramount.com | E43: approved | F43: Co-Head Games | G43: Paramount GLobal | H43: Media | I43: Jennifer.sharp@paramount.com | K43: https://www.linkedin.com/in/sharpjennifer/ | L43: na
A44: Iegor Ivanenko | D44: iegor@kavagaming.com | E44: approved | F44: CEO | G44: Kava Gaming Studio | H44: Game Studio | I44: iegor@kavagaming.com | K44: https://www.linkedin.com/in/iegor-ivanenko-53b04967?utm_source=share&utm_campaign=share_via&utm_content=profile&utm_medium=ios_app | L44: Roman
A45: Roman Bolshakov | B45: Roman | C45: Bolshakov | D45: partnership@kavagaming.com | E45: approved | F45: CEO | G45: Kava Gaming Studio | H45: Game Studio | I45: partnership@kavagaming.com | J45: @rbolshak | K45: https://www.linkedin.com/in/roman-bolshakov-20a8ab54?utm_source=share&utm_campaign=share_via&utm_content=profile&utm_medium=ios_app | L45: Kate
A46: Jenny Xu | B46: Jenny | C46: Xu | D46: jenny@talofagames.com | E46: approved | F46: CEO | G46: Talofa Games | H46: Game Studio | I46: Jenny@talofagames.com | J46: Jennycxu | K46: https://www.linkedin.com/in/xujennyc | L46: Max kaufman
A47: konstantinos zarkadoulas | B47: Kostas | C47: Zrk | D47: kostaszrk99@gmail.com | E47: approved | F47: Analyst | G47: Gaming Crypto | H47: Media | I47: kostaszrk99@gmail.com | K47: https://www.linkedin.com/in/konstantinos-zarkadoulas-%F0%9F%94%9Cgamescom-094681204?utm_source=share&utm_campaign=share_via&utm_content=profile&utm_medium=ios_app | L47: Max Kaufman
A48: Martyn Hughes | D48: martyn@metaverseme.io | E48: approved | F48: CEO | G48: MetaverseME Ltd | H48: Infrastructure, Blockchain, Game Studio, Others | I48: martyn@metaverseme.io | J48: Staggan | K48: https://www.linkedin.com/in/hughesmartyn/ | L48: Max Kaufman
A49: Michael Kabat | B49: Michael | C49: Kabat | D49: kabat@wondermakers.digital | E49: approved | F49: Co-Founder, CBO | G49: Wonder Makers (https://wondermakers.games) | H49: Infrastructure, Game Studio | I49: kabat@wondermakers.digital | J49: @Michael_Kabat | K49: https://linkedin.com/in/michaelkabat1 | L49: Max Kaufman
A50: Jason Kim | B50: Jason | C50: Kim | D50: jason.kim@to.nexus | E50: approved | F50: General Manager | G50: NEXUS (Cross Protocol) | H50: Blockchain, AI, Game Publisher, Game Studio | I50: jason.kim@to.nexus | J50: jason_dxb | K50: https://linkedin.com/in/jaeyoung-jason-kim-26a4b0128 | L50: UAE team
A51: Amy Wrigley | D51: amy.wrigley@discordapp.com | E51: approved | F51: Director of Business Development | G51: Discord | H51: Infrastructure | I51: amy.wrigley@discordapp.com | K51: https://www.linkedin.com/in/alangenstein/ | L51: Trapper Markelz
A52: Gunny Yoon | B52: Kunhee | C52: Yoon | D52: kunhee@blockus.gg | E52: approved | F52: Head of Gaming | G52: Blockus | H52: Infrastructure, Blockchain, Game Publisher | I52: kunhee@blockus.gg | J52: @gunyoon | K52: https://linkedin.com/in/yoonkunhee | L52: Max, Jon
A53: Sarah Parvini | B53: Sarah | C53: Parvini | D53: sparvini@activision.com | E53: approved | F53: Communications Lead | G53: Activision | H53: Game Publisher | I53: Sparvini@activision.com | K53: Sarahparvini | L53: LinkedIn invitation
A54: Merle | B54: Merle | D54: maxence.merle@gamearly.com | E54: approved | F54: CM & Social Media Manager | G54: GAMEARLY | H54: Others, Blockchain | I54: maxence.merle@gamearly.com | K54: https://www.linkedin.com/in/maxencemerle | L54: kamil zielinski
A55: Jimi Oh | B55: Jimi | C55: Oh | D55: jamesoh@com2us.com | E55: approved | F55: Director of Business Development | G55: Com2uS Platform | H55: Infrastructure, Game Publisher, Game Studio | I55: jamesoh@com2us.com | K55: https://www.linkedin.com/in/jimioh/ | L55: Jon
A56: Dorothy Ferguson | B56: Dorothy | C56: Ferguson | D56: dorothy.ferguson@strattonstudiogames.com | E56: approved | F56: Vice President Business Development | G56: Stratton Studio Games | H56: Game Studio | I56: DOROTHY.FERGUSON@STRATTONSTUDIOGAMES.COM | J56: #ERROR! | K56: https://www.linkedin.com/in/fergusond/ | L56: Max Kaufman
A57: Deniz Can Kose | B57: Deniz | C57: Can Kose | D57: d.kose@tap-nation.io | E57: approved | F57: Senior Project Manager, Alternative Stores | G57: TapNation | H57: Game Publisher | I57: d.kose@tap-nation.io | K57: https://www.linkedin.com/in/deniz-can-kose/ | L57: N/A
A58: Marc Bell | B58: Marc | C58: Bell | D58: marc@sabaientertainment.com | E58: approved | F58: Founder & Leisure technician | G58: Goldfinger Entertainment | H58: Blockchain, Media, Game Publisher, Game Studio, iGaming | I58: spindegens@cz4prez.com | J58: pimpsmoke | K58: https://www.linkedin.com/in/jmarcbell?utm_source=share&utm_campaign=share_via&utm_content=profile&utm_medium=ios_app | L58: Kamil and Sergio \m/
A59: Charles De Cendral | B59: Charles | C59: De Cendral | D59: charles.decendral@gamearly.com | E59: approved | F59: Gamearly | G59: Gamearly | H59: Others | I59: charles.decendral@gamearly.com | J59: @Cheated0x | K59: https://www.linkedin.com/in/charlesdecendral/ | L59: @kamilzielinski
A60: Aria Esrafilian | B60: Aria | C60: Esrafilian | D60: aria@troverse.io | E60: approved | F60: Founder | G60: Troverse (GameFi x GenAI | x.com/PlayTroverse) | H60: AI, Blockchain, Game Studio | I60: Aria@playtroverse.com | J60: @ariaesrafilian | K60: https://linkedin.com/in/ariaesrafilian | L60: GameFi project building on Polygon
A61: Berker Siino | B61: Berker | C61: Siino | D61: berkersiino@outlook.com | E61: approved | F61: Art Director | G61: MonsterPuppet | H61: Game Studio | I61: berker@monster-puppet.com | K61: https://www.linkedin.com/in/berkersiino/ | L61: Marcus
A62: Jeremy Parris | B62: Jeremy | C62: Parris | D62: jeremy@kingriver.co | E62: approved | F62: ventures/consulting | G62: King River Capital | H62: VC, Others | I62: jeremy@kingriver.co | J62: jeremystormsky | K62: https://www.linkedin.com/in/jeremy-parris-b242a4211/ | L62: know jon raddoff and a lot of the wolves
A63: Tommaso Jakob | B63: Tommaso | C63: Jakob | D63: tommaso.jakob@ubisoft.com | E63: approved | F63: Project Coordinator - ANNO Brand | G63: Ubisoft Mainz | H63: Game Studio | I63: tommaso.jakob@ubisoft.com | K63: https://www.linkedin.com/in/tommasojakob/ | L63: Haye Anderson
A64: Kristian Metzger | D64: kristian@stratosphere-games.com | E64: approved | F64: CEO | G64: Stratosphere Games GmbH | H64: Game Studio | I64: kristian@stratosphere-games.com | J64: @Khorneslayer24 | K64: https://linkedin.com/in/kristianmetzger | L64: Max Kaufman
A65: Tim Loosen | B65: Tim | C65: Loosen | D65: tim@lussa.io | E65: approved | F65: CBO | G65: Lussa | H65: Infrastructure | I65: Info@lussa.io | J65: @Powerlauch | K65: https://www.linkedin.com/in/tim-loo?utm_source=share&utm_campaign=share_via&utm_content=profile&utm_medium=android_app | L65: Jon Radoff
A66: Zlatko Stjepanović | B66: Zlatko | C66: Stjepanović | D66: zlatko@lussa.io | E66: approved | F66: CEO | G66: Lussa | H66: Infrastructure | I66: zlatko@lussa.io | J66: @zlatko369 | K66: https://www.linkedin.com/in/zlatko-z?utm_source=share&utm_campaign=share_via&utm_content=profile&utm_medium=android_app | L66: Jon Radoff
A67: Niels de Ruiter | B67: Niels | C67: de Ruiter | D67: hello@nielsderuiter.com | E67: approved | F67: Investor | G67: notneils | H67: VC | I67: hello@nielsderuiter.com | J67: noosoods | K67: https://www.linkedin.com/in/nielsderuiter1/ | L67: Max Kaufman (web3 frens group)
A68: MinChi Park | B68: Minchi | C68: Park | D68: park.minchi@gmail.com | E68: approved | F68: Head of Ecosystem | G68: HyperPlay | H68: Infrastructure, Blockchain | I68: minchi@hyperplay.xyz | K68: https://linkedin.com/in/minchipark | L68: Max
A69: Sydney Sharp | B69: Sydney | C69: Sharp | D69: ssharp@3thix.com | E69: approved | F69: Bd | G69: 3thix | H69: Blockchain, Infrastructure, Wallet | I69: Ssharp@3thix.com | J69: Sydneysharp | K69: https://www.linkedin.com/in/sydney--sharp | L69: Max Kaufman
A70: TIMOTHY R TELLO | B70: Timothy | C70: Tello | D70: ttello@3thix.com | E70: approved | F70: CEO | G70: 3thix | H70: Blockchain, Wallet, Infrastructure | I70: Ttello@3thix.com | J70: Tellotimothy | K70: https://www.linkedin.com/in/timothytello | L70: Max Kaufman
A71: Sebastien BORGET | B71: Sebastien | C71: Borget | D71: seb@sandbox.game | E71: approved | F71: Co-Founder | G71: The Sandbox | H71: Blockchain, Game Publisher | I71: seb@sandbox.game | J71: sebastienborget | K71: https://www.linkedin.com/in/borgetsebastien | L71: Max Kaufman
A72: Thomas Rössig | B72: Thomas | C72: Rössig | D72: thomas@roessig.biz | E72: approved | F72: Founder / Fractional CEO | G72: Game Founder Coach / Playing Mantis | H72: Game Studio | I72: thomas@roessig.biz | K72: https://www.linkedin.com/in/thomasroessig/ | L72: Not invited by someone, I used to run a studio in the web3 space.
A73: Robin Squire | B73: Robin | C73: Squire | D73: robin@blackbloxk.io | E73: approved | F73: CEO | G73: Black Block | H73: Game Studio, Infrastructure | I73: robin@blackblock.io | K73: https://www.linkedin.com/in/robin-squire | L73: Max Kaufman
A74: Anton Umnov | B74: Anton | C74: Umnov | D74: anton@helika.io | E74: approved | F74: Founder and CEO | G74: Helika | H74: Infrastructure, Game Publisher | I74: Anton@helika.io | K74: https://linkedin.com/in/anton-umnov | L74: Max
A75: Nahir | B75: Nahir | D75: mizuchin12@gmail.com | E75: approved | F75: CEO | G75: Dreams of Heaven Games | H75: Game Studio | I75: Mizuchin12@gmail.com | K75: https://linkedin.com/in/nahir-fajardo | L75: None
A76: Nate Dykstra | B76: Nate | C76: Dykstra | D76: nate.dykstra@mattel.com | E76: approved | F76: Business Development, Licensing | G76: Mattel | H76: Game Publisher | I76: nate.dykstra@mattel.com | K76: https://www.linkedin.com/in/natedykstra/ | L76: Giancarlo Rios
A77: Alex Tarrand | D77: alex@styngr.com | E77: approved | F77: COO | G77: STYNGR | H77: Media | I77: alex@styngr.com | J77: @alextarrand | K77: https://www.linkedin.com/in/alextarrand/ | L77: Grace
A78: Assad Dar | D78: assad.dar@moongaming.com | E78: approved | F78: Founder & CVO | G78: Medieval Empires | H78: Game Studio | I78: Assad.dar@gmail.com | J78: @assad_dar | K78: LinkedIn.com/in/assaddar | L78: Our $MEE token is on Polygon
A79: Rufus Kubica | D79: rufus.kubica@11bitstudios.com | E79: approved | F79: External Development Director | G79: 11 bit studios | H79: Game Publisher, Game Studio | I79: rufus.kubica@11bitstudios.com | K79: https://www.linkedin.com/in/rufus-kubica-9482b7a5/ | L79: Got the invite from our PR Team
A80: Oliver Löffler | B80: Oliver | C80: Löffler | D80: oliver@voya.games | E80: approved | F80: CEO | G80: VOYA Games | H80: Game Studio, Game Publisher | I80: oliver@voya.games | K80: https://www.linkedin.com/in/oliverloeffler/ | L80: Sai
A81: Luai Mahjneh | D81: luai.mahjneh@fennicagaming.com | E81: approved | F81: SVP | G81: Fennica Gaming | H81: Game Publisher | I81: luai.mahjneh@fennicagaming.com | K81: https://www.linkedin.com/in/luaimahjneh/ | L81: Tom Jaatinen
A82: Baptiste Granet | B82: Baptiste | C82: Granet | D82: baptiste.granet@immutable.com | E82: approved | F82: BD, EMEA Manager | G82: Immutable | H82: Blockchain | I82: baptiste.granet@immutable.com | J82: baptistegrnt | K82: https://linkedin.com/in/baptiste-granet | L82: No invite, but working with Sergio and Kamil on a regular basis
A83: Rana Rahman | B83: Rana | C83: Rahman | D83: rana@raptorpr.com | E83: approved | F83: CEO & Founder | G83: Raptor PR | H83: Media | I83: Rana@raptorpr.com | J83: @ranaraptor | K83: https://linkedin.com/in/ranaraptor | L83: Max Kaufman
A84: Joshua Callaghan | B84: Joshua | C84: Callaghan | D84: joshua@raptorpr.com | E84: approved | F84: Junior Account Manager | G84: Raptor PR | H84: Others | I84: joshua@raptorpr.com | K84: https://www.linkedin.com/in/joshua-callaghan/ | L84: Max Kaufman
A85: Mike Sanders | B85: Mike | C85: Sanders | D85: msanders@punyhuman.com | E85: approved | F85: Chief Development Officer | G85: Carbonated | H85: Game Studio | I85: msanders@punyhuman.com | J85: @urinalcake | K85: https://www.linkedin.com/in/mikerobyte/ | L85: Grace Zhou
A86: Dustin Brower | B86: Dustin | C86: Brower | D86: dustin@blueravenla.com | E86: approved | F86: Head of Brand Partnerships | G86: Blue Raven | H86: Others | I86: dustin@blueravenla.com | K86: https://www.linkedin.com/in/dustinbrower/ | L86: Grace Zhou
A87: Johnny Chua | B87: Johnny | C87: Chua | D87: johnny@lightningforge.games | E87: approved | F87: CCO | G87: Lightning Forge Games | H87: Game Studio, Blockchain | I87: johnny@lightningforge.games | J87: @Hit_Box_01 | K87: https://linkedin.com/in/jonathanjchua | L87: Max Kaufman
A88: Sean Shin | B88: Sean | C88: Shin | D88: seanshin@com2us.com | E88: approved | F88: Global BD Lead | G88: Com2uS Platform | H88: Game Studio | I88: seanshin@com2us.com | K88: https://www.linkedin.com/in/seonhoshin/ | L88: -
A89: Sky | B89: Sky | D89: sky@wolvesdao.io | E89: approved | F89: CTO | G89: Woof labs | H89: Others | I89: sky@wolvesdao.io | K89: https://www.linkedin.com/in/jonathan-bruenderman-4ba5151b/ | L89: Payton Kaleiwahea
A90: Serhat MARASLIGIL | B90: Serhat | C90: Marasligil | D90: smar@sequence.xyz | E90: approved | F90: Senior Producer | G90: Sequence | H90: Blockchain, Infrastructure, Wallet | I90: Smar@sequence.xyz | J90: Themarasligil | K90: https://www.linkedin.com/in/serhatmarasligil?utm_source=share&utm_campaign=share_via&utm_content=profile | L90: Max Kaufman
A91: Brian McWilliams | D91: brian@wildblueberrygames.com | E91: approved | F91: CEO | G91: Wild Blueberry Games | H91: Game Studio | I91: brian@wildblueberrygames.com | J91: @BrianMcWilliams | K91: https://www.linkedin.com/in/brian-mcwilliams-b68b63b8/ | L91: Michael Sanders shared the event with me
A92: Saad Zaeem | B92: Saad | C92: Zaeem | D92: saad@revolvinggames.com | E92: approved | F92: CEO | G92: Revolving Games | H92: Game Publisher | I92: saad@revolvinggames.com | K92: https://linkedin.com/in/saadzaeem | L92: Shreyansh
A93: Eujin OH | B93: Eujin | C93: Oh | D93: eujin@com2us.com | E93: approved | F93: Marketing Manager | G93: Com2us Platform | H93: Game Publisher, Game Studio, Infrastructure | I93: eujin@gmail.com | K93: https://www.linkedin.com/in/eujinoh/ | L93: Sunho Shin
A94: Clementine AH-GON | B94: Clementine | C94: Ah-Gon | D94: clementine.ah-hon@ubisoft.com | E94: approved | F94: Junior International Product Manager | G94: Ubisoft Mainz | H94: Game Studio | I94: clementine.ah-hon@ubisoft.com | K94: https://www.linkedin.com/in/clementine-ah-hon/ | L94: Haye Anderson
A95: David An | B95: David | C95: An | D95: david@dracoon.ventures | E95: approved | F95: Managing Partner | G95: Dracoon Ventures | H95: VC, Blockchain | I95: david@dracoon.ventures | J95: davidkendo | K95: https://linkedin.com/in/davidan | L95: BGA
A96: Mel | B96: Mel | C96: Dow | D96: melanie@blockchaingamealliance.net | E96: approved | F96: Comms and BD | G96: Blockchain Game Alliance | H96: Blockchain | I96: Melanie@blockchaingamealliance.net | K96: https://linkedin.com/in/melanie-dow | L96: Sergio
A97: Gabriela Siemienkowicz | B97: Gabriela | C97: Siemienkowicz | D97: gabriela.siemienkowicz@11bitstudios.com | E97: approved | F97: Communications Lead | G97: 11 Bit Studios | H97: Game Publisher, Game Studio | I97: gabriela.siemienkowicz@11bitstudios.com | J97: Poland | K97: https://www.linkedin.com/in/gabriela-siemienkowicz/ | L97: Jason Ying
A98: Laurens | B98: Laurens | C98: Lauwverse | D98: lamastijgen@gmail.com | E98: approved | F98: CPO | G98: WolvesDAO | H98: Media | I98: Lauw@wolvesdao.io | K98: http://linkedin.com/in/laurensverweij | L98: Wolvesdao
A99: Gabriel Stürmer | D99: gabriel@clapclap.games | E99: approved | F99: CEO | G99: 👏 Clap 👏 Clap Games | H99: Game Publisher | I99: gabriel@clapclap.games | K99: https://www.linkedin.com/in/gabrielsturmer/ | L99: --
A100: Daniel Bowen | B100: Daniel | C100: Bowen | D100: dan.bowen@stash.gg | E100: approved | F100: Growth Lead | G100: Stash | H100: Others | I100: Dan.bowen@stash.gg | K100: https://www.linkedin.com/in/daniel-bowen-?utm_source=share&utm_campaign=share_via&utm_content=profile&utm_medium=ios_app | L100: Max Kaufman
...

Sheet RSVPs - Aug 13
A1: name | B1: first_name | C1: last_name | D1: email | E1: approval_status | F1: Job Title | G1: Company | H1: Type of Company | I1: Email | J1: Telegram | K1: What's your LinkedIn ? | L1: Kindly provide the name of the person who invited you to this event
A2: Jakub Vambersky | B2: Jakub | C2: Vambersky | D2: jvambersky@madfingergames.com | E2: approved | F2: Lead Community Manager | G2: MADFINGER Games | H2: Game Studio | I2: jvambersky@madfingergames.com | K2: https://www.linkedin.com/in/jakub-vambersky-%F0%9F%94%9C-gamescom-99179312b/ | L2: Dominik Jícha
A3: Mariano Rubinstein | B3: Mariano | C3: Rubinstein | D3: mr@suragaming.com | E3: approved | F3: CEO & Co-founder | G3: Sura Gaming | Sura Ventures | H3: Game Studio, Wallet, VC | I3: mr@suragaming.com | K3: https://linkedin.com/in/marianorubinstein | L3: Sergio Varona
A4: Rick Lagnese | B4: Rick | C4: Lagnese | D4: rlagnese@madfingergames.com | E4: approved | F4: PR Director | G4: MADFINGER Games | H4: Game Studio | I4: rlagnese@madfingergames.com | K4: https://www.linkedin.com/in/rick-lagnese/ | L4: Dominik Jicha
A5: jorge jimenez | B5: Jorge | C5: Jimenez | D5: jorge@thegamingstrategist.com | E5: approved | F5: CEO | G5: The Gaming Strategist | H5: Media | I5: jorge@thegamingstrategist.com | J5: thegamingstrategist | K5: https://linkedin.com/company/the-gaming-strategist | L5: payton
A6: Rob Esom | B6: Rob | C6: Esom | D6: rob@swiperight.gg | E6: approved | F6: Director, Games Publishing and Tech | G6: Swipe Right | H6: Game Publisher | I6: rob@swiperight.gg | K6: https://www.linkedin.com/in/robert-esom-8b1bb7120/ | L6: Amy White
A7: Alfredo Bárcena | B7: Alfredo | C7: Bárcena | D7: alfredobarcena@merso.io | E7: approved | F7: Head of EMEA | G7: Merso.io | H7: Others, Blockchain | I7: alfredobarcena@merso.io | J7: @alfredobarcena | K7: https://www.linkedin.com/in/alfredo-b%C3%A1rcena-guti%C3%A9rrez-de-ter%C3%A1n-%F0%9F%94%9C-gamescom-cologne-23a9b415/ | L7: Sergio Varona
A8: David Magnier | B8: David | C8: Magnier | D8: david.magnier@mrkite.io | E8: approved | F8: Head of BD & Growth | G8: Youmio / TODAY The Game | H8: AI, Game Studio | I8: david.magnier@mrkite.io | K8: https://linkedin.com/company/mrkite | L8: Michael O'Connor
A9: Kun Gao | B9: Kun | C9: Gao | D9: kun@forge.gg | E9: approved | F9: CEO | G9: Forge | H9: Infrastructure | I9: kun@forge.gg | K9: https://linkedin.com/in/kungao | L9: Polygon
A10: Gabriel Perez | B10: Gabriel | C10: Perez | D10: gabriel@forge.gg | E10: approved | F10: Head of BD and Partnership | G10: Forge.gg | H10: Others | I10: gabriel@forge.gg | J10: grperez | K10: https://www.linkedin.com/in/gabrielrperez/ | L10: Sergio
A11: Domenik Maier | B11: Domenik | C11: Maier | D11: dm@strayshot.game | E11: approved | F11: Ceo | G11: iBLOXX | H11: Game Studio | I11: Dm@strayshot.game | J11: iBloxx | K11: https://www.linkedin.com/in/domenik-maier-%F0%9F%94%9C-gamescom-a291ab130?utm_source=share&utm_campaign=share_via&utm_content=profile&utm_medium=ios_app | L11: Linkedin
A12: Robin Squire | B12: Robin | C12: Squire | D12: robin@blackblock.io | E12: approved | F12: CEO | G12: Black Block | H12: Game Studio, Infrastructure | I12: robin@blackblock.io | J12: @robinblackblock | K12: https://www.linkedin.com/in/robin-squire?utm_source=share&utm_campaign=share_via&utm_content=profile&utm_medium=ios_app | L12: Max Kaufman
A13: Paul Van Eijden | B13: Paul | C13: Van Eijden | D13: paul@cre8labs.io | E13: approved | F13: CTO | G13: CRE8 LABS | H13: Game Studio | I13: paul@cre8labs.io | K13: paulvaneijden | L13: Beamable
A14: Sylvain Loe-Mie | B14: Sylvain | C14: Loe-Mie | D14: sylvain.loe-mie@ubisoft.com | E14: approved | F14: Executive Producer | G14: Ubisoft | H14: Game Studio, Game Publisher | I14: Sylvain.loe-mie@ubisoft.com | K14: https://linkedin.com/in/sloemie | L14: Noone
A15: Doyi Kim | B15: Doyi | C15: Kim | D15: doyi@opengamefoundation.org | E15: approved | F15: Head of U.S. | G15: Opengame Foundation | H15: Blockchain, Game Publisher, Game Studio | I15: doyi@opengamefoundation.org | K15: https://www.linkedin.com/in/doyikim22/ | L15: Malcolm
A16: James Wing | B16: James | C16: Wing | D16: james.wing@mystenlabs.com | E16: approved | F16: Gaming Partnerships | G16: Mysten Labs | H16: Blockchain | I16: james.wing@mystenlabs.com | J16: stvrgeon | K16: https://www.linkedin.com/in/jamesmwing/ | L16: Ryan MacKeen
A17: Dan Bunting | B17: Dan | C17: Bunting | D17: dan@1amgaming.com | E17: approved | F17: Venture Partner | G17: 1AM Gaming | H17: VC | I17: dan@1amgaming.com | J17: 13109909709 | K17: https://linkedin.com/in/danbunting | L17: Grace Zhou event list
A18: Berube | C18: Berube | D18: berube@hellogiant.com | E18: approved | F18: Co-Founder | CCO | G18: Hello Giant | H18: Game Studio | I18: berube@hellogiant.com | K18: https://www.linkedin.com/in/jonathan-berube-avtr/ | L18: Grace Zhou event list
A19: Samuel j Steffanina | B19: Samuel | C19: Steffanina | D19: samsteffanina@gmail.com | E19: approved | F19: Chief Marketing Officer | G19: WolvesDAO / Remix | H19: Game Studio, Media | I19: samsteffanina@gmail.com | J19: samsteffanina1 | K19: linkedin.com/in/samsteffanina | L19: Payton Kalewahea
A20: Sarah Chafer | B20: Sarah | C20: Chafer | D20: s.chafer@xsolla.com | E20: approved | F20: Global Head of Sales, Xsolla Ads | G20: Xsolla | H20: Media | I20: s.chafer@xsolla.com | J20: United States | K20: https://www.linkedin.com/in/sarahprescottchafer/ | L20: Travis Anderson
A21: Lauren Baca | B21: Lauren | C21: Baca | D21: l.baca@xsolla.com | E21: approved | F21: VP of Marketing, Xsolla | G21: Xsolla | H21: Others | I21: l.baca@xsolla.com | K21: https://www.linkedin.com/in/laurenfrisciabaca/ | L21: Travis Anderson
A22: dub | B22: Andrew | C22: Wion | D22: dub@glittercloud.solutions | E22: approved | F22: Co-Founder | G22: Glitter Cloud Solutions | H22: Game Publisher | I22: dub@glittercloud.solutions | J22: uhhdub | K22: https://www.linkedin.com/in/andrew-dub-wion-064683b0/ | L22: Payton
A23: Oliver | B23: Oliver | C23: Maroney | D23: oliver.maroney@opensea.io | E23: approved | F23: Head of BD | G23: OpenSea | H23: Infrastructure | I23: Oliver.maroney@opensea.io | J23: @olivermaroney | K23: olivermaroney | L23: Payton
A24: Jacob Vandevelde | B24: Jacob | C24: Vandevelde | D24: jacob.vandevelde@sony.com | E24: approved | F24: Manager, Product Development | G24: SIE, PlayStation | H24: Others, Game Publisher, Game Studio | I24: jacob.vandevelde@sony.com | K24: https://www.linkedin.com/in/jacobvandevelde/ | L24: Sam Pottinger
A25: Si Lakos | B25: Si | C25: Lakos | D25: simon.lakos@mrkite.io | E25: approved | F25: VP Content | G25: Youmio | H25: AI | I25: Simon.lakos@mrkite.io | K25: https://linkedin.com/company/mrkite | L25: Peyton
A26: Sean Kauppinen | B26: Sean | C26: Kauppinen | D26: imseank@gmail.com | E26: approved | F26: Chief Strategy Officer | G26: Game industry LLC | H26: Game Studio | I26: imseank@gmail.com | J26: SeanWeb3 | K26: https://www.linkedin.com/in/seank/ | L26: Connor and Declan
A27: Ana | B27: Ana | C27: Touza Medina | D27: ana@onbeam.com | E27: approved | F27: PSM | G27: Beam | H27: Blockchain | I27: ana@onbeamc.om | J27: @AnaMaTM | K27: https://linkedin.com/in/am-tm | L27: Mike
A28: Andrea De Cunto | B28: Andrea | C28: De Cunto | D28: dek@molokstudios.com | E28: approved | F28: CEO | G28: Molok studios | H28: Others, Game Publisher | I28: dek@molokstudios.com | J28: 393914880943 | K28: https://www.linkedin.com/in/andreadecunto/ | L28: Max Behringer
A29: Jillian Mood | B29: Jillian | C29: Mood | D29: jillian.mood@gmail.com | E29: approved | F29: HR & Marketing | G29: Pomme | H29: Game Studio | I29: jillian@pommeconsultants.com | K29: https://www.linkedin.com/in/hrwonderwoman/ | L29: Jon
A30: Didier Mayda | B30: Didier | C30: Mayda | D30: didier.mayda@ubisoft.com | E30: approved | F30: Producer | G30: Ubisoft | H30: Game Studio, Game Publisher | I30: Didier.mayda@ubisoft.com | J30: @DragoncelloIM | K30: https://linkedin.com/in/didier-mayda-b6887415 | L30: Wolves
A31: Mark Tarrisse | B31: Mark | C31: Tarrisse | D31: mark.tarrisse@ubisoft.com | E31: approved | F31: Art director | G31: Ubisoft | H31: Game Publisher | I31: mark.tarrisse@ubisoft.com | K31: https://fr.linkedin.com/in/mark-tarrisse-8238761b | L31: wolves
A32: Brian Rohaly | D32: brian@alwaysgeekygames.com | E32: approved | F32: VP Marketing | G32: Voxies | H32: Game Studio | I32: brian@alwaysgeekygames.com | K32: https://www.linkedin.com/in/rohaly/ | L32: Sergio Varona
A33: Aaron Fletcher | D33: aaron.fletcher@sony.com | E33: approved | F33: Director | G33: PlayStation | H33: Game Publisher | I33: Aaron.fletcher@sony.com | K33: https://www.linkedin.com/in/aaron7?utm_source=share&utm_campaign=share_via&utm_content=profile&utm_medium=android_app | L33: Jacob Vandevelde
A34: Nikolaj Yatsyshyn | B34: Nikolaj | C34: Yatsyshyn | D34: nikolaj@kavagaming.com | E34: approved | F34: CTO | G34: Kava Gaming Studio | H34: Game Studio | I34: Nikolaj@kavagaming.com | K34: https://www.linkedin.com/in/nikolaj-yatsyshyn-12865920a/ | L34: Roman
A35: Abhir Das | D35: abhir@playsuper.club | E35: approved | F35: Founder | G35: PlaySuper Software Solutions Pvt. Ltd | H35: Infrastructure | I35: abhir@playsuper.club | J35: @iamabhir2709 | K35: https://www.linkedin.com/in/abhirdas/ | L35: Shreyansh
A36: Veronika Kotková | B36: Veronika | C36: Kotková | D36: vkotkova@madfingergames.com | E36: approved | F36: Community Manager | G36: MADFINGER Games | H36: Game Studio | I36: vkotkova@madfingergames.com | K36: https://www.linkedin.com/in/veronika-kotkova/ | L36: Dominik Jicha
A37: Yulia Bukareva | B37: Yulia | C37: Bukareva | D37: bukareva@playgama.com | E37: approved | F37: Head of Business Development | G37: Playgama.com | H37: Game Publisher | I37: bukareva@playgama.com | K37: https://www.linkedin.com/in/jbukareva/ | L37: spreadsheet with public events
A38: Valeria Svistunova | B38: Valeria | C38: Svistunova | D38: valeria.svistunova@playgama.com | E38: approved | F38: Head of Monetization | G38: Playgama.com | H38: Game Publisher | I38: valeria.svistunova@playgama.com | K38: https://www.linkedin.com/in/valeria-svistunova/ | L38: Julia
A39: Dmitry Kachmar | B39: Dmitry | C39: Kachmar | D39: monnaboter@gmail.com | E39: approved | F39: Founder | G39: Playgama.com | H39: Game Publisher | I39: monnaboter@gmail.com | J39: @dkachmar | K39: https://www.linkedin.com/in/dmitry-kachmar-84392725/ | L39: Yulia
A40: Jean-Philippe Saulnier | D40: jp@alwaysgeekygames.com | E40: approved | F40: COO | G40: AlwaysGeeky Games | H40: Game Studio, Blockchain | I40: jp@alwaysgeekygames.com | J40: @jpsaulnier | K40: jpsaulnier | L40: Sergio Varona
A41: Di�rik Steinsson | D41: didrik@porcelainfortress.com | E41: approved | F41: Founder | G41: Porcelain Fortress | H41: Game Studio, Game Publisher | I41: didrik@porcelainfortress.com | K41: https://www.linkedin.com/in/didriksteinsson | L41: Sir ChanceaLot
A42: Patrick Lu | B42: Patrick | C42: Lu | D42: patrick@playfull.com | E42: approved | F42: CEO | G42: Playfull | H42: Infrastructure, Blockchain | I42: Patrick@playfull.com | J42: @p3tricks | K42: https://linkedin.com/in/patrickmlu | L42: Julia + Payton
A43: James Hursthouse | B43: James | C43: Hursthouse | D43: james@greenstone.one | E43: approved | F43: Founder & CEO | G43: Greenstone Initiatives | H43: Infrastructure, AI, iGaming, Game Studio | I43: james@greenstone.one | J43: t/me/jameshursthouse | K43: https://linkedin.com/in/jameshursthouse | L43: Jon Radoff / Max Kaufman
A44: Benjamin Ben Hattar | B44: Benjamin | C44: Hattar | D44: benjamin.benhattar@gmail.com | E44: approved | F44: Founder and CTO | G44: Sleepless Games (TON Battleground) | H44: Game Studio | I44: benjamin.benhattar@gmail.com | J44: @Benjamin_Ben_Hattar | K44: https://linkedin.com/in/benhattar | L44: Alfredo Barcena
A45: Roman Arkharov | B45: Roman | C45: Arkharov | D45: roman.arkharov@playgama.com | E45: approved | F45: Software Engineer | G45: Playgama | H45: Game Publisher, Market Maker | I45: roman.arkharov@playgama.com | K45: https://www.linkedin.com/in/roman-arkharov-389baa37/ | L45: Yulia Bukareva
A46: Tony Gascon | B46: Tony | C46: Gascon | D46: tony@artchop.net | E46: approved | F46: Managing Director | G46: Artchop! | H46: Game Studio | I46: tony@artchop.net | K46: https://linkedin.com/in/tonygascon | L46: Ali El Rhermoul
A47: Upamanyu Chatterjee | B47: Upamanyu | C47: Chatterjee | D47: upamanyu@playsuper.club | E47: approved | F47: founder & CEO | G47: PlaySuper | H47: Infrastructure, Others | I47: upamanyu@playsuper.club | K47: https://www.linkedin.com/in/upamanyu-chatterjee/ | L47: Abhir Das
A48: Casey | Soulbound TV | B48: Casey | C48: G | D48: casey@soulbound.gg | E48: approved | F48: Founder | G48: Soulbound.TV | H48: Media, Infrastructure, iGaming | I48: casey@soulbound.gg | K48: https://linkedin.com/in/caseygrooms | L48: Max
A49: Shannon Maguire | B49: Shannon | C49: Maguire | D49: shannon@audiomob.com | E49: approved | F49: Global Head of Marketing | G49: Audiomob | H49: iGaming | I49: shannon@audiomob.com | K49: https://www.linkedin.com/in/shannon-maguire-35b10a22b/ | L49: Oscar Clark
A50: Tom | B50: Tom | C50: Cichocki | D50: tom@revived.game | E50: approved | F50: Founder & CEO | G50: Revived Overworld | H50: Game Studio | I50: tom@revived.game | J50: tomrevived | K50: https://linkedin.com/in/tomrevived | L50: Sergio
A51: Ilya Tikhomirov | B51: Ilya | C51: Tikhomirov | D51: ilya@playgama.com | E51: approved | F51: Co-Founder, COO | G51: Playgama.com | H51: Game Publisher | I51: ilya@playgama.com | K51: https://www.linkedin.com/company/playgama/ | L51: Yulia
A52: Andrew Carter | B52: Andrew | C52: Carter | D52: andrewc@glindagames.com | E52: approved | F52: VP Production and Business Development | G52: Glinda Games Pty Ltd | H52: Game Studio | I52: andrewc@live.com.sg | K52: https://www.linkedin.com/in/andrew-carter-%F0%9F%98%80-5797b348/ | L52: Jens Schroeder (IGEA)
A53: Montrieul Martin | B53: Montrieul | C53: Martin | D53: martin.montrieul@gmail.com | E53: approved | F53: Senior Game Designer | G53: Ubisoft | H53: Game Studio | I53: martin.montrieul@gmail.com | K53: https://www.linkedin.com/in/martinmontrieul/ | L53: wolves
A54: Mark Peterson | B54: Mark | C54: Peterson | D54: cpo@spectarium.games | E54: approved | F54: CPO | G54: Spectarium Games | H54: Game Studio | I54: cpo@spectarium.games | K54: https://www.linkedin.com/in/speaksgaming/ | L54: Parker Heath
A55: ryan buck | B55: Ryan | C55: Buck | D55: ryan@tripunk.com | E55: approved | F55: ceo | G55: Tripunk LTD | H55: Game Studio | I55: ryan@tripunk.com | K55: https://www.linkedin.com/in/ryan-buck-%F0%9F%94%9C-gamescom-devcom-475514270/ | L55: Grace Zhou
A56: Adam Harrison | B56: Adam | C56: Harrison | D56: adam@tripunk.com | E56: approved | F56: Unreal Developer | G56: TriPunk | H56: Game Studio | I56: Adam@tripunk.com | K56: https://www.linkedin.com/in/adamharrison92 | L56: Grace Zhou
A57: Maxim Shashkov | B57: Maxim | C57: Shashkov | D57: max@toontube.co | E57: approved | F57: CEO | G57: MOZUMA | H57: Media | I57: max@toontube.co | J57: @Maxxsh | K57: https://www.linkedin.com/in/maxim-shashkov/ | L57: Kamil Zielinski
A58: Gabriel Parent | B58: Gabriel | C58: Parent | D58: gabriel.parent@edgegap.com | E58: approved | F58: Marketing Director | G58: Edgegap | H58: Infrastructure | I58: gabriel.parent@edgegap.com | K58: https://www.linkedin.com/in/gabriel-parent-95583713/ | L58: Trapper Markelz
A59: Mafalda Duarte | D59: mafaldapd@gmail.com | E59: approved | F59: Ambassador Program Coordinator | G59: Women In Games | H59: Others | I59: mafaldapd@gmail.com | K59: https://www.linkedin.com/in/mafaldapduarte/ | L59: André Bernhardt
A60: Nauman Mulla | B60: Nauman | C60: Mulla | D60: nauman@getstan.app | E60: approved | F60: Co-founder & COO | G60: STAN | H60: Blockchain, Game Publisher | I60: nauman@getstan.app | K60: https://www.linkedin.com/in/nauman-mulla-%F0%9F%94%9C-gamescom-39b717a1?lipi=urn%3Ali%3Apage%3Ad_flagship3_profile_view_base_contact_details%3BfLijtFaBTzK%2BgQ%2FWDZfFeA%3D%3D | L60: Michael
A61: Jason Lepine | B61: Jason | C61: Lepine | D61: jason@xpsummit.ca | E61: approved | F61: Founder & CEO | G61: XP Gaming Inc | H61: Others | I61: jason@xpgaming.biz | K61: https://linkedin.com/in/xpjason | L61: Trapper Markelz
A62: Yuriy Yarovoy | B62: Yuriy | C62: Yarovoy | D62: yuriy@medal.tv | E62: approved | F62: SVP, Growth | G62: Medal | H62: Game Publisher, Others | I62: yuriy@medal.tv | K62: https://www.linkedin.com/in/yuriyyarovoy | L62: Grace
A63: Max Mayrock | B63: Max | C63: Mayrock | D63: max@rockawaygames.com | E63: approved | F63: Founder | G63: Rockaway Games | H63: Game Publisher, Game Studio | I63: max@rockawaygames.com | J63: United States | K63: www.LinkedIn.com/in/MaxMayrock | L63: Event List Provided to Me
A64: Alejandro Marin Vidal | B64: Alejandro | C64: Marin Vidal | D64: alejandro.marin.vidal@disney.com | E64: approved | F64: Director, Strategy & Insights | G64: Disney | H64: Media | I64: alejandro.marin.vidal@disney.com | K64: https://www.linkedin.com/in/dromv/ | L64: saw on events list
A65: Michael Mairs | B65: Michael | C65: Mairs | D65: smirkon16@gmail.com | E65: approved | F65: Twitch Ambassador / Content Creator | G65: Smirky | H65: Media, Others | I65: smirkon16@gmail.com | J65: @Michael1616 | K65: https://linkedin.com/in/michael-mairs | L65: N/A - Discovered via Search
A66: Declan | B66: Declan | C66: McCrea-Steele | D66: declan.mccreasteele@immutable.com | E66: approved | F66: Global Head of BD | G66: Immutable | H66: Blockchain | I66: declan.mccreasteele@immutable.com | J66: declanms | K66: https://www.linkedin.com/in/declan-mccrea-steele-30796953/overlay/background-image/ | L66: Kamil
A67: Lemz Lizard | B67: Lemz | C67: Lizard | D67: lemz42@riseup.net | E67: approved | F67: Marketing | G67: WolvesDAO | H67: Infrastructure, Others | I67: lemz42@riseup.net | J67: @Lemz42 | K67: https://www.linkedin.com/company/wolvesdao/ | L67: Payton (I am also a part of the WolvesDAO core team)
A68: Tanya Priyank | B68: Tanya | C68: Priyank | D68: tanya.priyank@showheroes.com | E68: approved | F68: VP of Business Development | G68: ShowHeroes SE | H68: Media | I68: tanya.priyank@showheroes.com | K68: https://de.linkedin.com/in/tanyapriyank | L68: Alex Rosales
A69: Shilpa | B69: Shilpa | C69: Menon | D69: shilpa.menon@kwalee.com | E69: approved | F69: Sr. Manager- Business Development | G69: Kwalee | H69: Game Publisher | I69: shilpa.menon@kwalee.com | K69: linkedin.com/in/shilpa-menon-🔜-gamescom-72a99651 | L69: Company got an invite
A70: Jacopo Pietro Gallelli | D70: j.gallelli@dymstudios.com | E70: approved | F70: CEO | G70: Dynamight Studios S.r.l. | H70: Game Studio | I70: contact@dymstudios.com | J70: Italy | K70: https://www.linkedin.com/in/jacopo-pietro-gallelli/ | L70: -
A71: Cengizhan Can | D71: cengizhancan@microsoft.com | E71: approved | F71: Cloud Solution Architect | G71: Microsoft | H71: Infrastructure | I71: cengizhancan@microsoft.com | K71: cengi | L71: Grace Zhou
A72: Monika Yosifoba | B72: Monika | C72: Yosifova | D72: monika@bottledmonster.ink | E72: approved | F72: Founder | G72: Bottled Monster Ink | H72: Game Studio | I72: monika@bottledmonster.ink | K72: https://www.linkedin.com/in/monika-yosifova-95351311b/ | L72: N/A
A73: Ammar Zaeem | B73: Ammar | C73: Zaeem | D73: ammar@revolvinggames.com | E73: approved | F73: Co-CEO | G73: Revolving Games | H73: Game Studio, Game Publisher, Blockchain | I73: ammar@revolvinggames.com | K73: https://www.linkedin.com/in/ammarzaeem | L73: -
A74: Cody Bye | B74: Cody | C74: Bye | D74: cody.bye@overwolf.com | E74: approved | F74: General Manager | G74: Nitro, an Overwolf company | H74: Media | I74: cody.bye@overwolf.com | K74: https://www.linkedin.com/in/codybye/ | L74: No one specifically
A75: Sophia Tran | B75: Sophia | C75: Tran | D75: info@sophia-tran.de | E75: approved | F75: Founder & CEO | G75: Spotlight! Ventures | H75: VC, Media | I75: Info@sophia-tran.de | K75: https://linkedin.com/in/sophia_tran | L75: Jon Radoff
A76: Daniel Laurence Visser | B76: Daniel | C76: Laurence Visser | D76: danielv@glindagames.com | E76: approved | F76: Managing Director | G76: Glinda Games PTY LTD, AU | H76: Game Studio | I76: danielv@glindagames.com | K76: https://www.linkedin.com/in/danielvisser/ | L76: IGEA
A77: CryptoSlavvv | B77: Vanja | C77: Čokić | D77: cryptoslavvv@gmail.com | E77: approved | F77: Founder, Ceo, Creative Director | G77: Infinite Runs, Cypocalypse | H77: iGaming, Infrastructure, Blockchain, AI | I77: cryptoslavvv@gmail.com | J77: cryptoslavvv | K77: https://linkedin.com/in/vvanja | L77: Malcolm Chang
A78: Jonathan Breeschooten | B78: Jonathan | C78: Breeschooten | D78: jonathan@nevalence.com | E78: approved | F78: Founder - Manager iCrazyTeddy | G78: Nevalence | H78: Media | I78: jonathan@nevalence.com | J78: ZeroLoops | K78: https://linkedin.com/in/jonathanbreeschooten | L78: None
A79: Max Záruba | B79: Max | C79: Záruba | D79: mzaruba@madfingergames.com | E79: approved | F79: Marketing Video Artist | G79: MADFINGER Games | H79: Game Studio | I79: mzaruba@madfingergames.com | K79: https://www.linkedin.com/in/max-z%C3%A1ruba-b1442b147?utm_source=share&utm_campaign=share_via&utm_content=profile&utm_medium=ios_app | L79: Dominik Jícha - CMO of MADFINGER Games
A80: SEOKJIN YONG | B80: Seokjin | C80: Yong | D80: seokjinyong@com2us.com | E80: approved | F80: Hive Solutions Architect team, Assistant Manager | G80: Com2uS Platform Corp | H80: Game Publisher | I80: seokjinyong@com2us.com | K80: www.linkedin.com/in/seokjinyong-b5a961378 | L80: David Mohr
A81: Elyot Grant | B81: Elyot | C81: Grant | D81: elyot@lunarchstudios.com | E81: approved | F81: CEO and Game Director | G81: Lunarch Studios | H81: Game Studio | I81: elyot@lunarchstudios.com | K81: https://www.linkedin.com/in/elyotgrant | L81: Grace Zhou
A82: Jakub Marek | B82: Jakub | C82: Marek | D82: jakub@numucollective.com | E82: approved | F82: CEO | G82: Numu Collective | H82: AI, Game Publisher | I82: jakub@numucollective.com | K82: https://www.linkedin.com/in/jakub-marek-sk/ | L82: Hannibal
A83: Thomas Chenu | D83: thomas.chenu.linkedin@gmail.com | E83: approved | F83: CEO | G83: Mirage Line Entertainment | H83: Others | I83: thomas.chenu.linkedin@gmail.com | K83: https://www.linkedin.com/in/thomas-chenu-e/ | L83: Daniel Tabar
A84: Babatunde Adam Oluwalana | B84: Babatunde | C84: Adam Oluwalana | D84: baba@heroic.gg | E84: approved | F84: Producer | G84: HEROIC | H84: Others, Media | I84: baba@heroic.gg | K84: https://www.linkedin.com/in/babatundeadam/ | L84: Krystian Jaroszynski
A85: Richard | D85: richard@valueofwe.com | E85: approved | F85: Managing Director | G85: Value of We GmbH | H85: iGaming | I85: richard@valueofwe.com | K85: https://www.linkedin.com/in/richard-petrich-711b71113/ | L85: Found it through some event list and would like to join as we represent Web3 for Jägermeister and BMW M
A86: Jakub Vambersky | B86: Jakub | C86: Vambersky | D86: jvambersky@madfingergames.com | E86: approved | F86: Lead Community Manager | G86: MADFINGER Games | H86: Game Studio | I86: jvambersky@madfingergames.com | K86: https://www.linkedin.com/in/jakub-vambersky-%F0%9F%94%9C-gamescom-99179312b/ | L86: Dominik Jícha
A87: Oliver Warren | B87: Oliver | C87: Warren | D87: ollie.warren@unity3d.com | E87: approved | F87: Senior Solution Architect | G87: Unity | H87: Infrastructure | I87: ollie.warren@unity3d.com | K87: https://www.linkedin.com/in/ollie-warren-080306143/ | L87: Diego Beltrame
A88: Philippe Robert | B88: Philippe | C88: Robert | D88: philippe@tarokai.com | E88: approved | F88: CEO | G88: Tarokai | H88: Game Studio | I88: philippe@tarokai.com | K88: https://www.linkedin.com/in/philippe-robert-peachfarmer/ | L88: Baptiste Granet
A89: Lucie Colin | B89: Lucie | C89: Colin | D89: contact@tarokai.com | E89: approved | F89: COO | G89: tarokai | H89: Game Studio | I89: contact@tarokai.com | K89: https://www.linkedin.com/in/luciecolinrobert/ | L89: Baptiste granet
A90: funza | B90: funza | D90: funza15@gmail.com | E90: approved | F90: Customer Suport | G90: MADFINGER games | H90: Game Studio | I90: funza15@gmail.com | K90: https://www.linkedin.com/in/jan-nechvatal/ | L90: Dominik Jicha
A91: Dominik Jícha | B91: Dominik | C91: Jícha | D91: djicha@madfingergames.com | E91: approved | F91: Marketing Director | G91: MADFINGER Games, a.s. | H91: Game Publisher, Game Studio | I91: djicha@madfingergames.com | K91: https://www.linkedin.com/in/dominikjicha/ | L91: Found myself
A92: Hannibal Soares | B92: Hannibal | C92: Soares | D92: hannibal@boomland.io | E92: approved | F92: CEO | G92: BoomLand | Web3 Game Publishing | H92: Game Publisher | I92: Hannibal@boomland.io | K92: https://linkedin.com/in/hannibalsoares | L92: Max Kaufman
A93: Vitalii Vashchuk | B93: Vitalii | C93: Vashchuk | D93: vitalii@vashchuk.org | E93: approved | F93: Vice President, Global Head of Gaming | G93: EPAM | H93: Infrastructure, AI | I93: vitalii_vashchuk@epam.com | J93: vit.vas1 | K93: https://linkedin.com/in/vashchukvitalii | L93: Grace Zhou or use Jon Radoff
A94: Jas Singh | B94: Jas | C94: Singh | D94: jas@lightningforge.games | E94: approved | F94: Head of Marketing | G94: Lightning Forge Games | H94: Game Studio | I94: jas@lightningforge.games | J94: brains_ct | K94: https://www.linkedin.com/in/jasvir-singh-06119b1b7/ | L94: Max Kaufman
A95: Long Chu | B95: Long | C95: Chu | D95: long@ggwp.com | E95: approved | F95: VP Ops | G95: GGWP | H95: AI | I95: long@ggwp.com | K95: https://www.linkedin.com/in/longchu88/ | L95: Joi Podgorny
A96: Kathleen Sherman | B96: Kathleen | C96: Sherman | D96: kathleen.sherman@lysto.io | E96: approved | F96: Senior Game Partnerships Manager at Lysto | G96: Lysto | H96: Others | I96: kathleen.sherman@lysto.io | K96: https://www.linkedin.com/in/kathleen-sherman/ | L96: n/a
A97: Travis Anderson | B97: Travis | C97: Anderson | D97: t.anderson@xsolla.com | E97: approved | F97: Head of Developer Partnerships | G97: Xsolla | H97: Infrastructure, Blockchain, Game Publisher, VC | I97: t.anderson@xsolla.com | K97: https://www.linkedin.com/in/travisandersonpro/ | L97: Sanket Shah
A98: Andrew Willson | B98: Andrew | C98: Willson | D98: andrew@makersfund.com | E98: approved | F98: General Partner | G98: Makers Fund | H98: VC | I98: andrew@makersfund.com | K98: https://linkedin.com/in/andrewjswillson | L98: Polygon team
A99: Sergei Vasiuk | B99: Sergei | C99: Vasiuk | D99: sergei@vasi.uk | E99: approved | F99: Product Director | G99: Wargaming | H99: Game Studio, Game Publisher | I99: sergei@vasi.uk | K99: https://www.linkedin.com/in/sergeivasjuk/ | L99: Grace Zhou
A100: JOI PODGORNY from GGWP | B100: Joi | C100: Podgorny | D100: joi@ggwp.com | E100: approved | F100: Marketing & Partnerships | G100: GGWP | H100: Infrastructure | I100: joi@ggwp.com | K100: https://linkedin.com/in/joipodgorny | L100: Event list
...

Sheet RSVPs - Aug 25
A1: name | B1: first_name | C1: last_name | D1: email | E1: approval_status | F1: Job Title | G1: Company | H1: Type of Company | I1: Email | J1: Telegram | K1: What's your LinkedIn ? | L1: Kindly provide the name of the person who invited you to this event
A2: Adam Straney | D2: adam@warped.games | E2: approved | F2: CEO | G2: Warped Games | H2: Game Studio | I2: Adam@warped.games | J2: Adam_warped | K2: Adamstraney | L2: Trapper
A3: Johannes Preis | B3: Johannes | C3: Preis | D3: johannes.preis@hator.gg | E3: approved | F3: Brand Director | G3: HATOR | H3: Others | I3: Johannes.preis@hator.gg | K3: https://www.linkedin.com/in/johannes-preis-144728104?utm_source=share&utm_campaign=share_via&utm_content=profile&utm_medium=android_app | L3: Tom Lemke
A4: Erik J. Caponi | B4: Erik | C4: J. Caponi | D4: erik.caponi@splashdamage.com | E4: approved | F4: Creative Director | G4: Splash Damage | H4: Game Studio | I4: erik.caponi@splashdamage.com | K4: https://www.linkedin.com/in/ecaponi | L4: Discovered on a list of events
A5: Joanna Rycyk | D5: joanna.rycyk@tatemultimedia.com | E5: approved | F5: Head of Production | G5: Tate Multimedia | H5: Game Publisher | I5: joanna.rycyk@tatemultimedia.com | K5: https://www.linkedin.com/in/joanna-rycyk-026593159?utm_source=share&utm_campaign=share_via&utm_content=profile&utm_medium=android_app | L5: Paweł Łaskarzewski
A6: Andy Dee | B6: Andy | C6: Dee | D6: acrossfy@gmail.com | E6: approved | F6: Founder, CEO | G6: Overtroll | H6: Game Studio | I6: Andy@overtroll.com | K6: https://www.linkedin.com/in/andrey-dyakov | L6: Who knows?)
A7: Turan Selvi | B7: Turan | C7: Selvi | D7: turan@clipster.gg | E7: approved | F7: Founder | G7: Clipster | H7: Media | I7: turan@clipster.gg | J7: saikyo | K7: https://www.linkedin.com/in/turan-selvi?utm_source=share&utm_campaign=share_via&utm_content=profile&utm_medium=ios_app | L7: Max Kaufmann
A8: Levi Romanov | B8: Levi | C8: Romanov | D8: levi.romanov@immutable.com | E8: approved | F8: Head of Americas | G8: Immutable | H8: Blockchain | I8: Levi.romanov@immutable.com | K8: https://www.linkedin.com/in/leviromanov | L8: Declan Steele
A9: Elsa Tung | B9: Elsa | C9: Tung | D9: elsa.tung@showheroes.com | E9: approved | F9: senior international BD manager | G9: ShowHeroes SE | H9: Media | I9: elsa.tung@showheroes.com | K9: https://www.linkedin.com/in/elsatung?utm_source=share&utm_campaign=share_via&utm_content=profile&utm_medium=ios_app | L9: tugrul
A10: Dilara Kececi | B10: Dilara | C10: Kececi | D10: dilara@lorienaccelerator.com | E10: approved | F10: Managing Partner | G10: Lorien Accelerator | H10: VC | I10: dilara@lorienaccelerator.com | K10: https://linkedin.com/in/dilarakececi | L10: Can Gunaslan
A11: Gonca Ertaner | B11: Gonca | C11: Ertaner | D11: gonca.ertaner@gmail.com | E11: approved | F11: CRM & Digital Innovation Manager | G11: Samsung Elwctronics GmbH | H11: AI, Others | I11: gonca.ertaner@gmail.com | J11: Deutschland | K11: https://www.linkedin.com/in/gonca-ertaner?utm_source=share&utm_campaign=share_via&utm_content=profile&utm_medium=android_app | L11: Laurin Bylica
A12: Yoav Sochen | B12: Yoav | C12: Sochen | D12: yoav@sochen.org | E12: approved | F12: Esports production Manager | G12: Freelance - former Riot Games | H12: Media | I12: yoav@sochen.org | K12: https://www.linkedin.com/in/yoav-sochen/ | L12: Krystian Jaroszynski
A13: Can Gunaslan | B13: Can | C13: Gunaslan | D13: can.gunaslan@gmail.com | E13: approved | F13: Senior Marketing Manager | G13: Google | H13: AI, Infrastructure | I13: cangunaslan@google.com | K13: https://www.linkedin.com/in/cgunaslan | L13: Bella
A14: Murphy | B14: Murphy | D14: murphy@imts.vip | E14: approved | F14: CEO | G14: Immortals Studios | H14: Game Studio | I14: murphy@imts.vip | K14: MurphyYang | L14: Kamil Zielinski
A15: Tom Lemke | B15: Tom | C15: Lemke | D15: tl@savagetech.gg | E15: approved | F15: Founder | G15: SavageTech | H15: iGaming | I15: Tl@savagetech.gg | K15: https://www.linkedin.com/in/tom-jang-lemke-33118499?utm_source=share&utm_campaign=share_via&utm_content=profile&utm_medium=android_app | L15: Max kaufmann
A16: Can Florian Ahegger | B16: Florian | C16: Ahegger | D16: ca@ca-agentur.com | E16: approved | F16: CEO | G16: ca agentur via Samsung | H16: Media, Others, Blockchain | I16: Ca@ca-agentur.com | J16: Uniquecol888 | K16: https://www.linkedin.com/in/can-florian-ahegger?utm_source=share&utm_campaign=share_via&utm_content=profile&utm_medium=ios_app | L16: Sandeep Nailwal
A17: Michael O'Connor | B17: Michael | C17: O'Connor | D17: michael.oconnor@mrkite.io | E17: approved | F17: Ceo | G17: Youmio | H17: AI | I17: Michael.oconnor@mrkite.io | K17: Mjoc9 | L17: Max, Jon
A18: Guga Zagonel | B18: Guga | C18: Zagonel | D18: guga@kreativitasstudio.com | E18: approved | F18: Ceo | G18: Kreativitas | H18: Game Studio | I18: Guga@kreativitasstudio.com | K18: https://linkedin.com/in/guga-zagonel | L18: Slack
A19: Gleb Skibitsky | B19: Gleb | C19: Skibitsky | D19: gleb@walletconnect.com | E19: approved | F19: Gaming Lead | G19: WalletConnect / Reown | H19: Infrastructure, Wallet | I19: gleb@walletconnect.com | K19: https://www.linkedin.com/in/skibitsky?utm_source=share&utm_campaign=share_via&utm_content=profile | L19: Olli from Voya games
A20: Oleg Suptelia | B20: Oleg | C20: Suptelia | D20: o.suptelia@4taleproduction.com | E20: approved | F20: CEO | G20: 4tale production | H20: Game Studio | I20: O.suptelia@4taleproduction.com | J20: @t4dxx | K20: https://www.linkedin.com/in/sugunwar | L20: Miomigames web3 developers
A21: keith cook | B21: Keith | C21: Cook | D21: keith@getspaceport.com | E21: approved | F21: Head of BD and Licensing | G21: Spaceport | H21: Others | I21: Keith@getspaceport.com | K21: Keithcook | L21: Craig Zevin
A22: Millie Yang | B22: Millie | C22: Yang | D22: millie@breeze.cash | E22: approved | F22: CEO | G22: Breeze | H22: Infrastructure | I22: Millie@breeze.cash | K22: LinkedIn.com/in/millieyang | L22: Jon radoff
A23: Philip Pan | B23: Philip | C23: Pan | D23: philip@breeze.cash | E23: approved | F23: Head of Payments | G23: Breeze | H23: iGaming, Infrastructure | I23: Philip@breeze.cash | K23: Linkedin.com/in/pfpan | L23: Serena
A24: Alvaro Gil | B24: Alvaro | C24: Gil | D24: alvaro.gil@tiktok.com | E24: approved | F24: BD Director | G24: Tiktok | H24: Media | I24: Alvaro.gil@tiktok.com | K24: Linkedin | L24: Slack
A25: Marcin | B25: Marcin | D25: marcin@revived.game | E25: approved | F25: Business Developer | G25: Revived Overworld | H25: Game Studio | I25: marcin@revived.game | K25: https://www.linkedin.com/in/marcin-oliwkowski-1665ab46?utm_source=share&utm_campaign=share_via&utm_content=profile&utm_medium=android_app | L25: Kamil Zielinski
A26: Chris Dawson | D26: chris@styngr.com | E26: approved | F26: CPO | G26: STYNGR | H26: Infrastructure, Others | I26: chris@styngr.com | J26: United Kingdom | K26: https://www.linkedin.com/in/chris-d-487b4321/ | L26: Alex Terrand
A27: Rudy Koch | B27: Rudy | C27: Koch | D27: rudy@joagames.io | E27: approved | F27: Co-founder | G27: JOA | H27: Infrastructure, Blockchain, AI, Game Studio | I27: rudy@joagames.io | K27: https://www.linkedin.com/in/rudykoch | L27: Shreyansh
A28: Matthew Conn | D28: matthew@vyersoft.com | E28: approved | F28: president | G28: Curse Free Studios/VYERSOFT | H28: Media | I28: Matthew@vyersoft.com | J28: Xxlsol | K28: mrmattconn | L28: Sergio
A29: Denis Matusovskiy | D29: denis.matusovskiy@streamscharts.com | E29: approved | F29: Partnerships Manager | G29: Streams Charts | H29: Infrastructure, Media | I29: denis.matusovskiy@streamscharts.com | K29: https://www.linkedin.com/in/denis-matusovskiy | L29: Max Kaufman
A30: Ana | B30: Ana | D30: anastasia@esm.one | E30: approved | F30: Partnerships & Sponsorships Manager | G30: Esports & Streams Charts | H30: Others | I30: anastasia@esm.one | K30: https://www.linkedin.com/in/anastasiia-kaidalova/ | L30: Max Kaufman
A31: Efe | B31: Efe | C31: Kucuk | D31: efekucuk@gmail.com | E31: approved | F31: Head of Gaming | G31: Tezos | H31: Blockchain | I31: efe.kucuk@trili.tech | J31: itsefekucuk | K31: https://linkedin.com/in/efekucuk | L31: None
A32: Sevilay Catakli | B32: Sevilay | C32: Catakli | D32: sevilay.catakli@icloud.com | E32: approved | F32: EA to CEO | G32: Epitome MMORPG: https://epitomegame.com | H32: Game Studio, AI | I32: sevilay.catakli@icloud.com | K32: https://www.linkedin.com/in/nickvalentino33 | L32: Nick
A33: Nicolas Valentino Smigielski | B33: Nicolas | C33: Valentino Smigielski | D33: nick@epitome.studio | E33: approved | F33: CEO | G33: Epitome MMORPG: https://epitomegame.com | H33: Game Studio, AI | I33: nick@epitome.studio | K33: https://linkedin.com/in/nickvalentino33 | L33: Mark
A34: Timur Tugambay | B34: Timur | C34: Tugambay | D34: timur@onetwoplay.games | E34: approved | F34: Co-founder | G34: OneTwoPlay | H34: Blockchain, Game Studio | I34: Timurtugambay@gmail.com | J34: @carboc | K34: https://www.linkedin.com/in/timur-tugambay?utm_source=share&utm_campaign=share_via&utm_content=profile&utm_medium=android_app | L34: Self registration
A35: Craig | B35: Craig | C35: Zevin | D35: craig@getspaceport.com | E35: approved | F35: COO | G35: Spaceport Technologies | H35: Blockchain, Infrastructure | I35: Craig@spaceport.xyz | J35: @whatupcraig | K35: https://linkedin.com/in/craig-zevin | L35: Angie
A36: Bella Flowers | B36: Bella | C36: Flowers | D36: bella@offbase.com | E36: approved | F36: Creative Marketing Manager | G36: Off Base | H36: Others, Media | I36: bella@offbase.com | J36: 17077411923 | K36: https://linkedin.com/in/bellaflowers | L36: n/a
A37: Dirk Schepens | B37: Dirk | C37: Schepens | D37: dirk@xspectar.com | E37: approved | F37: CEO | G37: MetaVentures SA - xSPECTAR | H37: iGaming, Game Studio | I37: dirk@xspectar.com | J37: @ds198200 | K37: None | L37: Kamil - Sergio
A38: Elyssa Grant | D38: egrlynt@justin.tv | E38: approved | F38: Senior Content Manager, Events | G38: Twitch | H38: Media | I38: egrlynt@twitch.tv | K38: Elyssagrant | L38: Amy White
A39: Toby Allen | B39: Toby | C39: Allen | D39: toby@jobsingames.com | E39: approved | F39: CEO | G39: StartupMill | H39: Game Studio | I39: Toby@startupmill.com | K39: LinkedIn.com/in/tobyallen | L39: Max
A40: Tabarak Paracha | D40: tabarak@tenjin.com | E40: approved | F40: Marketing Manager and BDM | G40: Tenjin | H40: Market Maker | I40: tabarak@tenjin.com | K40: https://www.linkedin.com/in/tabarak-paracha-%F0%9F%94%9C-gamescom-cologne-766b3a113/ | L40: Linkedin
A41: Julia Happymiaow | B41: Julia | C41: Happymiaow | D41: julia.happymiaow@bravezebra.com | E41: approved | F41: Business Developement MAnager | G41: Brave Zebra | H41: Game Studio | I41: Julia.happymiaow@bravezebra.com | K41: https://www.linkedin.com/in/julia-happymiaow/ | L41: axel
A42: Zen Wilder | B42: Zen | C42: Wilder | D42: zen@wilderworld.com | E42: approved | F42: Head of Partnerships | G42: Wilder World | H42: Game Studio | I42: zen@wilderworld.com | K42: https://www.linkedin.com/in/maximilian-celebi-a8062333/ | L42: Sam Steffanina
A43: Mochtar-Jan Noori | B43: Mochtar-Jan | C43: Noori | D43: mochtarnoori123@outlook.de | E43: approved | F43: Builder | G43: WolvesDAO | H43: Blockchain, AI | I43: mochtarnoori123@outlook.de | J43: Deutschland | K43: Mochtar | L43: WolvesDAO
A44: Niklas Faust | B44: Niklas | C44: Faust | D44: nf@niklasfaust.com | E44: approved | F44: GC | G44: Klang Games GmbH | H44: Game Studio | I44: Nf@niklasfaust.com | J44: @niklasfaust | K44: LinkedIn.com | L44: Jon Radoff
A45: George Elhabr | B45: George | C45: Elhabr | D45: george@appagent.com | E45: approved | F45: Mobile Growth | G45: AppAgent | H45: Media, Market Maker, Others | I45: george@appagent.com | K45: http://LinkedIn.com/in/georgehbr | L45: Francesca Belfiore
A46: Linda CARLSON | B46: Linda | C46: Carlson | D46: linda.carlson@dps.gg | E46: approved | F46: Head of CX | G46: Distinct Possibility Studios | H46: Game Studio | I46: Linda.carlson@dps.gg | J46: 12505744628 | K46: LinkedIn.com/in/Brasse | L46: Abhi Pawa, CEO of AP Collective
A47: Lydian Feneck | B47: Lydian | C47: Feneck | D47: lydian.feneck@gamearly.com | E47: approved | F47: CEO | G47: AMEARLY | H47: Others | I47: lydian.feneck@gamearly.com | J47: @Fenlyd | K47: https://www.linkedin.com/in/lydian-feneck/ | L47: Kamil Zielinski
A48: Pavel | B48: Pavel | C48: Paulenka | D48: pavel.paulenka@elympics.ai | E48: approved | F48: BD | G48: Elympics | H48: Blockchain, Infrastructure, Game Studio | I48: pavel.paulenka@elympics.ai | J48: kartoha_elympics | K48: https://www.linkedin.com/in/pavel-paulenka-🔜-gamescom-573402188 | L48: Stanisław Fiedor
A49: Alex Kirichenko | B49: Alex | C49: Kirichenko | D49: alexey@vialex.tv | E49: approved | F49: co-founder | G49: Vialex Motion Lab | H49: Game Studio | I49: alexey@vialex.tv | K49: http://linkedin.com/in/alexey-kirichenkomotionlab | L49: Sergio Varona
A50: Victoria | D50: victoria@vialex.tv | E50: approved | F50: CEO | G50: Vialex Motion Lab | H50: Game Studio | I50: victoria@vialex.tv | K50: http://linkedin.com/in/victoria-vialexmotion | L50: Sergio Varona
A51: Poorya Shafiei | B51: Poorya | C51: Shafiei | D51: blue@zipclash.io | E51: approved | F51: COO | G51: IdleMoonLabs | H51: Game Studio | I51: pooryashafiei@gmail.com | J51: Bluesama1 | K51: https://linkedin.com/in/pooryashafiei | L51: Ana from Beam
A52: David | B52: David | C52: O | D52: davissko@devmons.gg | E52: approved | F52: Investor | G52: Sigil fund, Devmons Gaming | H52: VC | I52: davissko@devmons.gg | K52: https://linkedin.com/in/david-odstr%C4%8Dil-660b941a1 | L52: Jon
A53: Colin McDonald | D53: colin@moonsworth.com | E53: approved | F53: Cofounder | G53: Moonsworth | H53: Game Studio | I53: colin@moonsworth.com | K53: colinmcdonald22 | L53: Jon Radoff
A54: Matt Fonseca (Lunar Client) | B54: Matt | C54: Fonseca | D54: matt@moonsworth.com | E54: approved | F54: Ceo | G54: Moonsworth | H54: Game Publisher, Game Studio | I54: Matt@moonsworth.com | K54: https://linkedin.com/in/matheusfonseca21 | L54: Jon Radoff
A55: Nicholas | B55: Nicholas | D55: veilcraft@mortalabs.com | E55: approved | F55: Co founder | G55: Mortal Labs | H55: Game Studio | I55: nicholas.zhou@mortalabs.com | J55: @nicholaszhou | K55: https://www.linkedin.com/in/nicholas-zhou-a22638176?utm_source=share&utm_campaign=share_via&utm_content=profile&utm_medium=ios_app | L55: Jon Radoff
A56: Patrick Schulte | B56: Patrick | C56: Schulte | D56: pschulte@3thix.com | E56: approved | F56: Head of sales | G56: 3thix | H56: Blockchain | I56: Pschulte@3thix.com | J56: Coachpatnft | K56: https://www.linkedin.com/in/patrickryanschulte?utm_source=share&utm_campaign=share_via&utm_content=profile&utm_medium=ios_app | L56: Jon
A57: Aldric Chang | B57: Aldric | C57: Chang | D57: aldric@mixedrealms.com | E57: approved | F57: CEO | G57: Mixed Realms | H57: Game Studio | I57: aldric@mixedrealms.com | K57: https://www.linkedin.com/in/aldricchang/ | L57: Jon Radoff
A58: Jawharah Alabdulqader | B58: Jawharah | C58: Alabdulqader | D58: jawharah@nomadroid.co | E58: approved | F58: CEO | G58: Nomadroid | H58: Game Studio | I58: Info@nomadroid.co | K58: https://www.linkedin.com/in/jawharah-alabdulqader?utm_source=share&utm_campaign=share_via&utm_content=profile&utm_medium=ios_app | L58: Jon Radoff
A59: Rafal | B59: Rafal | D59: rafal@metashiftlabs.com | E59: approved | F59: Co-founder & CEO | G59: Metashift Labs | H59: Game Studio | I59: rafal@metashiftlabs.com | K59: Rafbie | L59: Jon
A60: Daniel Romero | B60: Daniel | C60: Romero | D60: daniel@onbeam.com | E60: approved | F60: Investment Lead | G60: Merit Circle / Beam | H60: VC | I60: daniel@onbeam.com | J60: bambam_bammy | K60: https://www.linkedin.com/in/daniel-r-aa444b236?utm_source=share&utm_campaign=share_via&utm_content=profile&utm_medium=android_app | L60: Sam
A61: Frank | B61: Frank | C61: RECORDS | D61: hi@memerecords.co | E61: approved | F61: Founder & CEO | G61: MEME RECORDS | H61: Game Studio | I61: hi@memerecords.co | J61: @MEME_RECORDS | K61: https:/www.linkedin.com/in/frank-hamilton | L61: Ryan Mackeen
A62: Matt Schembari | B62: Matt | C62: Schembari | D62: matteo522@gmail.com | E62: approved | F62: CEO | G62: Lightforge | H62: Game Studio | I62: matteo522@gmail.com | K62: https://LinkedIn.com/in/matteo522 | L62: Mike
A63: Dan Whittam | B63: Dan | C63: Whittam | D63: dswhittam@hotmail.com | E63: approved | F63: Marketing Lead | G63: CanCanCanAMan | H63: Game Studio | I63: dswhittam@hotmail.com | J63: United Kingdom | K63: https://www.linkedin.com/in/danwhittam/ | L63: Ruby Innes
A64: Teddy | B64: Teddy | C64: Teddy | D64: icrazyteddy@gmail.com | E64: approved | F64: Founder - Content Phenom | G64: HYPE UNIT | H64: Media | I64: Icrazyteddy@gmail.com | J64: Icrayzteddy | K64: https://linkedin.com/in/abdul-samad-z-873986112 | L64: N/A
A65: Kohji Nagata | B65: Kohji | C65: Nagata | D65: kohji@parallelnft.com | E65: approved | F65: Founder | G65: Parallel | H65: Game Studio | I65: Kohji@parallelnft.com | K65: Kohjinagata | L65: Sam
A66: Theodor Diea | D66: theo@goosebyte.games | E66: approved | F66: CEO | G66: Goose Byte Studios Inc. | H66: Game Studio | I66: theo@goosebyte.games | K66: https://www.linkedin.com/in/theodordiea/ | L66: Michael Sanders
A67: Anas Assara | D67: anas@untamedvc.com | E67: approved | F67: Founder and Managing Partner at Untamed Ventures | G67: Untamed Ventures | H67: VC | I67: anas@untamedvc.com | J67: @UntamedVC | K67: https://www.linkedin.com/in/anas-a-0b11842b/ | L67: Ali El Rhemoul @ Beamable
A68: Devashish | B68: Devashish | C68: Sharma | D68: devashish@joinlvl.com | E68: approved | F68: Head of BD, ceo | G68: LVL | H68: Infrastructure | I68: devashish@joinlvl.com | K68: https://www.linkedin.com/in/devashishsharma | L68: -
A69: Matheus Cohen | D69: matheus@obitus.games | E69: approved | F69: Product Lead | G69: Obitus Games | Overknights | H69: Game Studio | I69: matheus@obitus.games | K69: https://www.linkedin.com/in/matheus-cohen/ | L69: Immutable
A70: Eric Williams | D70: eric.williams@transperfect.com | E70: approved | F70: VP, Global Sales | G70: Technicolor Games (A TransPerfect Studio) | H70: Game Studio | I70: eric.williams@transperfect.com | K70: https://www.linkedin.com/in/ericw1/ | L70: Max Kaufman
A71: Mariano Dominguez | B71: Mariano | C71: Dominguez | D71: mariano@obitus.games | E71: approved | F71: Growth & Business Lead | G71: Obitus Games - OverKnights (first title) | H71: Game Studio, Blockchain | I71: mariano@obitus.games | J71: @MarianoDom | K71: https://www.linkedin.com/in/mariano-dominguez-365a901a6?utm_source=share&utm_campaign=share_via&utm_content=profile&utm_medium=ios_app | L71: Saw the post on Wolves X and said I can’t miss this.
A72: Jonah Blake | B72: Jonah | C72: Blake | D72: jonahrblake@gmail.com | E72: approved | F72: Founder | G72: Sploot AI | H72: Media, AI | I72: jonahrblake@gmail.com | J72: JRBlake | K72: Jonahblake | L72: Wolves boys
A73: Efim Zhitomirskiy | B73: Efim | C73: Zhitomirskiy | D73: e@asteranova.com | E73: approved | F73: Partner | G73: Asteranova | H73: Blockchain, AI, Game Studio | I73: e@asteranova.com | J73: emadex | K73: efim-zhi | L73: Gudjan
A74: Anna Smolkina | B74: Anna | C74: Smolkina | D74: qdgb8ty2p2@privaterelay.appleid.com | E74: approved | F74: CMO | G74: Pollo - use opinions to connect | H74: Blockchain, Others, Game Studio, iGaming | I74: anna.smolkina@asteranova.com | J74: annyesmola | K74: https://linkedin.com/in/annasmolkina | L74: Gunjan
A75: James Trusler | B75: James | C75: Trusler | D75: jtrusler@worldwish.org | E75: approved | F75: Partnerships Lead | G75: Make-A-Wish International | H75: Others | I75: jtrusler@worldwish.org | K75: https://www.linkedin.com/in/james-trusler/ | L75: April Stallings
A76: Linn Søvig | D76: linn@work-work.no | E76: approved | F76: Project Manager | G76: Spawn Point Trondheim | H76: Infrastructure | I76: linn@work-work.no | K76: https://www.linkedin.com/in/linnsovig/ | L76: Chris Charla
A77: Matthew Scott | D77: matt.scott@littleorbit.com | E77: approved | F77: CEO | G77: Little Orbit | H77: Game Publisher | I77: matt.scott@littleorbit.com | J77: United States | K77: https://www.linkedin.com/in/mattpscott | L77: Nick Beckley
A78: MarkRevived | B78: Mark | C78: Remiszewski | D78: mark@revived.game | E78: approved | F78: BD | G78: Revived Overwolrd | H78: Game Studio | I78: Mark@revived.game | J78: @markrevived | K78: https://linkedin.com/in/markremiszewski | L78: Papi
A79: Alina | B79: Alina | C79: Gribanova | D79: alina@devotedstudios.com | E79: approved | F79: BD Director | G79: Devoted | H79: Game Studio | I79: alina@devotedstudios.com | K79: https://linkedin.com/in/alinagribanova | L79: Max Kaufman
A80: Winston Wright | B80: Winston | C80: Wright | D80: winston@valueofwe.com | E80: approved | F80: Head of Partnerships | G80: G2 Esports | H80: Others | I80: winston@valueofwe.com | K80: https://www.linkedin.com/in/winston-wright-74735842/ | L80: Richard Petrich
A81: Shayli Harrison | B81: Shayli | C81: Harrison | D81: shayli@mutani.io | E81: approved | F81: CEO | G81: Mutani | H81: Others | I81: shayli@mutani.io | J81: @Mutani_io | K81: https://www.linkedin.com/in/shayli-harrison/ | L81: No one specific - although I share many mutual connections, have been in Web3 since 2019 and launched a project with Venly on Polygon. Would love to join the party!
A82: Soo | B82: Soo | C82: Nahm | D82: soo@opengamefoundation.org | E82: approved | F82: director | G82: Opengame foundation | H82: Blockchain, Game Publisher, Infrastructure | I82: Soo@opengamefoundation.org | J82: Sunshinesoo | K82: Https://www.linkedin.com/in/yeon-soo-nahm | L82: Seb
A83: Duane Wilson-Clarke | B83: Duane | C83: Wilson-Clarke | D83: duane@discovered.ae | E83: approved | F83: Head of Immersive & Gaming | G83: Level up | H83: Others | I83: duane@discovered.ae | J83: @duaneofgames | K83: https://linkedin.com/in/duaneofgames | L83: Max Kaufman
A84: Kyle Heath | D84: kpheath24@gmail.com | E84: approved | F84: Gaming Lead | G84: Avalanche | H84: Blockchain | I84: kpheath24@gmail.com | K84: https://www.linkedin.com/in/parker-heath-b98b28157/ | L84: Greg Labuz
A85: Tiffany Lam | B85: Tiffany | C85: Lam | D85: tiffany.lam@unity3d.com | E85: approved | F85: Technical Account Manager | G85: Unity Technologies | H85: Infrastructure | I85: tiffany.lam@unity3d.com | K85: www.linkedin.com/in/tiffanyslam | L85: Diego Beltrame
A86: Paul Harfouche | B86: Paul | C86: Harfouche | D86: paul@viralcollab.com | E86: approved | F86: Co Founder | G86: Viral Collab | H86: Media | I86: paul@viralcollab.com | K86: https://www.linkedin.com/in/paul-harfouche-%F0%9F%94%9C-gamescom-68b421102/ | L86: Pierre Moisan
A87: Shady Ab | B87: Shady | C87: Ab | D87: shady@viralcollab.com | E87: approved | F87: Co Founder | G87: Viral Collab | H87: Media | I87: shady@viralcollab.com | K87: www.linkedin.com/in/shady-ab-cpa-🔜-gamescom-9b8301113 | L87: Pierre Moisan
A88: Lennart Roosendaal | B88: Lennart | C88: Roosendaal | D88: lennart@galacticentertainment.com | E88: approved | F88: Strategic Business Development | G88: Galactic Entertainment | H88: Game Studio | I88: lennart@galacticentertainment.com | J88: @lennartroosendaal | K88: https://www.linkedin.com/in/lennartroosendaal/ | L88: Sergio Varona
A89: John Smedley | B89: John | C89: Smedley | D89: smed@dps.gg | E89: approved | F89: CEO | G89: Distinct Possibility Studios | H89: Game Studio | I89: smed.dps.gg | J89: 18583863913 | K89: https://www.linkedin.com/in/john-smedley-7a33534/ | L89: Abhi Pawa - CEO, AP Collective
A90: Oliver Lewis | D90: oliver@chronicle.studio | E90: approved | F90: COO | G90: Chronicle Studios | H90: Media | I90: oliver@chronicle.studio | K90: https://www.linkedin.com/in/owlewis/ | L90: None.
A91: Matthew Woods | B91: Matt | C91: Woods | D91: matt@afkcreators.com | E91: approved | F91: CEO | G91: Afk | H91: Others | I91: matt@afkcreators.com | K91: https://www.linkedin.com/in/itsmattwoods/ | L91: Jacob Vandevelde
A92: Arslan Yaseen | B92: Arslan | C92: Yaseen | D92: arslan.yaseen@leonardo.ai | E92: approved | F92: Lead- Gaming EMEA | G92: Leonardo AI (part of Canva) | H92: AI | I92: arslan.yaseen@leonardo.ai | K92: https://www.linkedin.com/in/arslanmyaseen/ | L92: N/A
A93: Konrad | B93: Konrad | D93: k.zagorowski@omlgames.com | E93: approved | F93: Gameplay Designer | G93: One More Level | H93: Game Studio | I93: k.zagorowski@omlgames.com | K93: https://pl.linkedin.com/in/k-zagorowski | L93: Dalton
A94: Roman Pinskyi | B94: Roman | C94: Pinskyi | D94: r.pinskyi@51.games | E94: approved | F94: CMO | G94: 51 Games | H94: Game Publisher, Game Studio | I94: r.pinskyi@51.games | J94: @romanpinskyi | K94: https://www.linkedin.com/in/roman-pinskyi-a35061111/ | L94: Hrvoje Mitic
A95: Jakub Vambersky | B95: Jakub | C95: Vambersky | D95: jvambersky@madfingergames.com | E95: approved | F95: Lead Community Manager | G95: MADFINGER Games | H95: Game Studio | I95: jvambersky@madfingergames.com | K95: https://www.linkedin.com/in/jakub-vambersky-%F0%9F%94%9C-gamescom-99179312b/ | L95: Dominik Jícha
A96: Mariano Rubinstein | B96: Mariano | C96: Rubinstein | D96: mr@suragaming.com | E96: approved | F96: CEO & Co-founder | G96: Sura Gaming | Sura Ventures | H96: Game Studio, Wallet, VC | I96: mr@suragaming.com | K96: https://linkedin.com/in/marianorubinstein | L96: Sergio Varona
A97: Rick Lagnese | B97: Rick | C97: Lagnese | D97: rlagnese@madfingergames.com | E97: approved | F97: PR Director | G97: MADFINGER Games | H97: Game Studio | I97: rlagnese@madfingergames.com | K97: https://www.linkedin.com/in/rick-lagnese/ | L97: Dominik Jicha
A98: jorge jimenez | B98: Jorge | C98: Jimenez | D98: jorge@thegamingstrategist.com | E98: approved | F98: CEO | G98: The Gaming Strategist | H98: Media | I98: jorge@thegamingstrategist.com | J98: thegamingstrategist | K98: https://linkedin.com/company/the-gaming-strategist | L98: payton
A99: Rob Esom | B99: Rob | C99: Esom | D99: rob@swiperight.gg | E99: approved | F99: Director, Games Publishing and Tech | G99: Swipe Right | H99: Game Publisher | I99: rob@swiperight.gg | K99: https://www.linkedin.com/in/robert-esom-8b1bb7120/ | L99: Amy White
A100: Alfredo Bárcena | B100: Alfredo | C100: Bárcena | D100: alfredobarcena@merso.io | E100: approved | F100: Head of EMEA | G100: Merso.io | H100: Others, Blockchain | I100: alfredobarcena@merso.io | J100: @alfredobarcena | K100: https://www.linkedin.com/in/alfredo-b%C3%A1rcena-guti%C3%A9rrez-de-ter%C3%A1n-%F0%9F%94%9C-gamescom-cologne-23a9b415/ | L100: Sergio Varona
...

Sheet Data - July 23
A1: Type of Company | B1: Total Count | D1: Total RSVP Approved | E1: Total Pending | F1: Total Sign Ups
A2: Games | B2: 22 | D2: 59 | E2: 64 | F2: =D2+E2 -> 123
A3: Game Studio | B3: 16
A4: Infrastructure | B4: 12
A5: Blockchain | B5: 8
A6: Game Publisher | B6: 8
A7: Others | B7: 7
A8: AI | B8: 6
A9: VC | B9: 4
A10: Media | B10: 3
A11: Exchange | B11: 1
A12: Wallet | B12: 1

Sheet Data - July 30
A1: Type of Company | B1: Total Count | D1: Total RSVP Approved | E1: Total Pending | F1: Total Sign Ups
A2: Game Studio | B2: 36 | D2: 123 | E2: 103 | F2: 228
A3: Infrastructure | B3: 29
A4: Game Publisher | B4: 23
A5: Games | B5: 22
A6: Blockchain | B6: 18
A7: Others | B7: 15
A8: AI | B8: 11
A9: Media | B9: 9
A10: VC | B10: 7
A11: Wallet | B11: 4
A12: Exchange | B12: 1
A13: iGaming | B13: 1

Sheet Data - Aug 6
A1: Type of Company | B1: Total Count | C1: % Increase | F1: Total RSVP Approved | G1: Total Pending | H1: Total Sign Ups | J1: Notable Companies
A2: Game Studio | B2: 65 | C2: =(B2-'Data - July 30'!B2)/'Data - July 30'!B2 -> 0.80555556 | F2: 190 | G2: 134 | H2: 324 | J2: Wargaming
A3: Infrastructure | B3: 41 | C3: =(B3-'Data - July 30'!B3)/'Data - July 30'!B3 -> 0.4137931 | E3: # increase WoW | F3: =F2-'Data - July 30'!D2 -> 67 | G3: =G2-'Data - July 30'!E2 -> 31 | H3: =H2-'Data - July 30'!F2 -> 96 | J3: Activision
A4: Game Publisher | B4: 40 | C4: =(B4-'Data - July 30'!B4)/'Data - July 30'!B4 -> 0.73913043 | E4: % increase WoW | F4: =(F2-'Data - July 30'!D2)/'Data - July 30'!D2 -> 0.54471545 | G4: =(G2-'Data - July 30'!E2)/'Data - July 30'!E2 -> 0.30097087 | H4: =(H2-'Data - July 30'!F2)/'Data - July 30'!F2 -> 0.42105263 | J4: Twitch
A5: Blockchain | B5: 31 | C5: =(B5-'Data - July 30'!B5)/'Data - July 30'!B5 -> 0.40909091 | J5: TikTok
A6: Others | B6: 26 | C6: =(B6-'Data - July 30'!B6)/'Data - July 30'!B6 -> 0.44444444 | J6: Discord
A7: Games | B7: 25 | C7: =(B7-'Data - July 30'!B7)/'Data - July 30'!B7 -> 0.66666667 | J7: Com2Us
A8: AI | B8: 17 | C8: =(B8-'Data - July 30'!B8)/'Data - July 30'!B8 -> 0.54545455 | J8: Team Liquid
A9: Media | B9: 15 | C9: =(B9-'Data - July 30'!B9)/'Data - July 30'!B9 -> 0.66666667 | J9: Tilting Point
A10: VC | B10: 11 | C10: =(B10-'Data - July 30'!B10)/'Data - July 30'!B10 -> 0.57142857 | J10: Gameloft
A11: Wallet | B11: 6 | C11: =(B11-'Data - July 30'!B11)/'Data - July 30'!B11 -> 0.5 | J11: Griffin Gaming
A12: iGaming | B12: 4 | C12: =(B12-'Data - July 30'!B12)/'Data - July 30'!B12 -> 3 | J12: Ubisoft
A13: Exchange | B13: 1 | C13: =(B13-'Data - July 30'!B13)/'Data - July 30'!B13 -> 0 | J13: Krafton
J14: Carry1st
J15: Wemade / Wemix
J16: Xsolla
J17: Reddit
J18: TapNation
J19: Paramount Global

Sheet Data - Aug 13
A1: Type of Company | B1: Total Count | C1: % Increase | F1: Total RSVP Approved | G1: Total Pending | H1: Total Sign Ups | J1: Notable Companies
A2: Game Studio | B2: 100 | C2: =(B2-'Data - Aug 6'!B2)/'Data - Aug 6'!B2 -> 0.53846154 | F2: 287 | G2: 148 | H2: 435 | J2: Wargaming
A3: Infrastructure | B3: 53 | C3: =(B3-'Data - Aug 6'!B3)/'Data - Aug 6'!B3 -> 0.29268293 | E3: # increase WoW | F3: =F2-'Data - Aug 6'!F2 -> 97 | G3: =G2-'Data - Aug 6'!G2 -> 14 | H3: =H2-'Data - Aug 6'!H2 -> 111 | J3: Activision
A4: Game Publisher | B4: 62 | C4: =(B4-'Data - Aug 6'!B4)/'Data - Aug 6'!B4 -> 0.55 | E4: % increase WoW | F4: =(F2-'Data - Aug 6'!F2)/'Data - Aug 6'!F2 -> 0.51052632 | G4: =(G2-'Data - Aug 6'!G2)/'Data - Aug 6'!G2 -> 0.10447761 | H4: =(H2-'Data - Aug 6'!H2)/'Data - Aug 6'!H2 -> 0.34259259 | J4: Twitch
A5: Blockchain | B5: 41 | C5: =(B5-'Data - Aug 6'!B5)/'Data - Aug 6'!B5 -> 0.32258065 | J5: TikTok
A6: Others | B6: 37 | C6: =(B6-'Data - Aug 6'!B6)/'Data - Aug 6'!B6 -> 0.42307692 | J6: Discord
A7: Games | B7: 31 | C7: =(B7-'Data - Aug 6'!B7)/'Data - Aug 6'!B7 -> 0.24 | J7: Com2Us
A8: AI | B8: 21 | C8: =(B8-'Data - Aug 6'!B8)/'Data - Aug 6'!B8 -> 0.23529412 | J8: Team Liquid
A9: Media | B9: 25 | C9: =(B9-'Data - Aug 6'!B9)/'Data - Aug 6'!B9 -> 0.66666667 | J9: Tilting Point
A10: VC | B10: 13 | C10: =(B10-'Data - Aug 6'!B10)/'Data - Aug 6'!B10 -> 0.18181818 | J10: Gameloft
A11: Wallet | B11: 7 | C11: =(B11-'Data - Aug 6'!B11)/'Data - Aug 6'!B11 -> 0.16666667 | J11: Griffin Gaming
A12: iGaming | B12: 7 | C12: =(B12-'Data - Aug 6'!B12)/'Data - Aug 6'!B12 -> 0.75 | J12: Ubisoft
A13: Exchange | B13: 1 | C13: =(B13-'Data - Aug 6'!B13)/'Data - Aug 6'!B13 -> 0 | J13: Krafton
J14: Carry1st
J15: Wemade / Wemix
J16: Xsolla
J17: Reddit
J18: TapNation
J19: Paramount Global
J20: Disney
J21: Microsoft
J22: Sony

Sheet Data - Aug 25
A1: Type of Company | B1: Total Count | E1: Total RSVP Approved | F1: Total Pending | G1: Total Sign Ups | I1: Notable Companies
A2: Game Studio | B2: 143 | E2: 406 | F2: 168 | G2: =E2+F2 -> 574 | I2: Wargaming
A3: Game Publisher | B3: 67 | D3: # increase WoW | E3: =E2-'Data - Aug 13'!F2 -> 119 | F3: =F2-'Data - Aug 13'!G2 -> 20 | G3: =G2-'Data - Aug 13'!H2 -> 139 | I3: Activision
A4: Infrastructure | B4: 66 | D4: % increase WoW | E4: =(E2-'Data - Aug 13'!F2)/'Data - Aug 13'!F2 -> 0.41463415 | F4: =(F2-'Data - Aug 13'!G2)/'Data - Aug 13'!G2 -> 0.13513514 | G4: =(G2-'Data - Aug 13'!H2)/'Data - Aug 13'!H2 -> 0.31954023 | I4: Twitch
A5: Blockchain | B5: 55 | I5: TikTok
A6: Others | B6: 52 | I6: Discord
A7: Media | B7: 40 | I7: Com2Us
A8: AI | B8: 31 | I8: Team Liquid
A9: Games | B9: 31 | I9: Tilting Point
A10: VC | B10: 17 | I10: Gameloft
A11: iGaming | B11: 11 | I11: Griffin Gaming
A12: Wallet | B12: 8 | I12: Ubisoft
A13: Exchange | B13: 1 | I13: Krafton
I14: Carry1st
I15: Wemade / Wemix
I16: Xsolla
I17: Reddit
I18: TapNation
I19: Paramount Global
I20: Disney
I21: Microsoft
I22: Sony
I23: Google
